{"type":"FeatureCollection","features":[{"type":"Feature","id":"321311","properties":{"name":"宿豫区","cp":[118.330012,33.941071],"childNum":1},"geometry":{"type":"Polygon","coordinates":["@@HEJCDABEDGDGDCD@DAFCBA@CAC@ABCDAFC@BB@@@B@@@B@@@@@B@@B@@B@@@B@@@BB@@@@B@@@@BB@@@B@@@B@@@B@B@@@BB@@B@@@B@@@B@@@B@@@B@@@BA@@@@B@@@B@@@@AB@@@B@@@@@BA@@B@@@B@@A@@B@@@B@@@BA@@@@B@@@BA@@B@@@@@B@@AB@@@B@@@BA@@B@@@@@B@@@@@B@@@B@@@@AB@@@B@@@BB@@@@B@B@@@@@BB@@B@@@B@@@@BB@@@@BB@@@@B@@@BB@@@@B@@@B@@@@@B@@@@@@@B@@@@@B@@@@@@@@@B@@@@@@@B@@@@@@BBA@@@@BA@@@@BA@@@@B@@AB@@@@@B@@AB@@@B@@@@@B@@@@@@@BB@@@@B@@@@B@@@@BB@@@B@@B@@B@@@@@B@@@B@@B@AB@@@@@B@@@B@@AB@@@@@B@@@B@@AB@@@@@B@@@B@B@@@B@@AB@@@B@@@B@@@B@@@@@BA@@B@@@B@@@@@B@@@B@@@@@B@@@@@B@@@@@B@@B@@B@@@@@B@@B@@B@@@@@B@@BB@@@@@@@BB@@B@@@B@@B@@B@@@B@@BB@@@@AB@@A@@@A@@BA@@BAB@BABADCDABADADABCBAFADCDC@A@G@Q@ADGDEFMDKBADAPK`BP@B@JBN@P@P@JBBHDFHDTDTBN@RBB@J@DBF@F@D@DBD@BBD@F@D@D@D@B@B@D@H@F@HAD@H@NCHAJ@PCNCF@HAFAF@D@FCDABAD@D@F@H@DBF@BBHAFAHCHCHGFAD@JDHDFFDDDDFBH@HDJDJDPHJDJDPDH@BC@@B@@A@@@@@A@@B@@A@@@A@@@@@A@@@AB@@@@A@@@A@@@@@A@@@@@AB@@@@A@@@A@@@@AA@@@@A@@A@@A@@A@@A@@@@A@@A@@@A@@A@@B@@A@@@A@@@A@@BA@@@@@A@@@A@@BA@@@A@@@A@@@@BA@@@A@@@A@@@AB@@@@A@@@A@@@AB@@A@@@@@A@@@AB@@@@@BA@@@@B@@A@@B@@@@@BA@@@@B@@AB@@@@@BA@@@@B@@@@AB@@@@@BA@@B@@@@AB@@@@@@@BA@@B@@@@AB@@@@@BA@@@@B@@@BA@@@@B@@A@@B@@@@@@A@@B@@@@A@@B@@@@A@@@@@@BA@@@@@@@AB@@@@AB@@@@@@@@AB@@@@@@A@@@@@@@A@@@@@@@A@@@@@@@@@A@@@@@@@A@@@@@@@A@@@@@@@@@A@@@@@A@@@@@@@@@A@@@@@A@@@@@@@A@@@@@@@@@A@@@@@AB@@@@@B@@A@@@@@@BA@@@A@@@@@AB@@@@A@@@A@@B@@A@@@@@A@@BA@@@@@A@@B@@A@@@@@A@@BA@@@A@@@@BA@@@A@@@@@@AA@@@A@@@@@@@A@@@@A@@A@@@@@AA@@@@A@@A@@@@A@@@@@AA@@@@A@@A@@A@@A@@@@@A@@@A@@@@A@@@@@@@AA@@@@@@@@A@@@@AA@@@@@@@A@@A@@A@@@@@@@A@@@@A@@@@@A@@@A@@@@@A@@@@@A@@@@@@@A@@BA@@@@@@AA@@@@A@@@A@@@@@A@@@A@@@A@@A@@A@@@A@@@A@@@A@@@A@@@@@A@@@@@AB@@A@@B@@@@@B@@@BA@@B@@@B@@@B@@@B@@@B@@@@@B@@AB@B@@@B@@@B@@@@@B@BA@@B@@@@@@AB@@@@A@@@@@A@@@A@@@@@A@@BA@@@@@A@@BAB@@A@@BA@@@@@A@@@A@@@@@@BA@@@A@@@@@A@@@A@@B@@A@@@@@A@@@A@@@@BA@@@@@A@@@@@A@@@AB@@@@A@@@@@A@@@@@AB@@A@@@@@A@@@A@@@@BA@@@@@A@@@A@@@@@AB@@@@A@@@@@A@@@A@@B@@A@@@@@@@A@@@@@@@@BA@@@@@A@@@@@A@@@@@A@@BA@@@A@@@A@@@A@@@@@AB@@A@@@A@@@A@@@A@@B@@A@@@@@A@@B@@@@A@@@@B@@A@@@@BA@@@@@AB@@@@@B@@@@A@@@@@@@A@@@@@A@@@@@A@@@@@@@A@@@@@A@@@@A@@AA@@@A@@@@A@@AA@@@@@@AA@@@A@@@@@AA@@@@AA@@@AA@@@@AA@@@@@A@@@@@A@@@@@AA@@A@@@@@AA@@@@A@@@AA@@@@@@A@@@@@@@A@@@@@A@@@@@@@@@A@@@@A@@A@@@@AA@@@@@AA@@A@@@A@@@@@AA@@A@@@A@@@@BA@@@A@@@A@@B@@A@@@A@@B@@A@@@@B@@A@@@@@A@@@@@A@@@@@@AA@@@@@A@@@@@A@@@@@A@@@@@A@@@@@A@@@@@A@@A@@@@A@@@@@A@@@AA@@@@A@@A@@@@@AA@@@@@A@@AA@@@@@@BA@@@@@A@@@@B@@@@@@@BA@@@@B@@@@@B@@@@@B@@@B@@@B@@@@@B@@@@@@AB@@@@@BA@@B@@@@@B@@@@@BA@@B@@@B@@@@AB@@@@@B@@@B@@A@@B@@@@A@@@A@@@@@A@@@A@@@@@A@@@@@A@@@A@@@A@@@@@A@@@A@@@@@A@@@@@A@@@A@@A@@@@@A@@@@@A@@@A@@@AA@@A@@@@@AA@@@@@@@A@@AA@@@@@A@@@@@A@@@@@A@@@@@@@AB@@@@@@A@@@@@A@@@@@@@A@@B@@A@@@@@@@AA@@@@@@A@@@@@@@@@A@@@@@A@@A@@A@@@@@@A@@A@@A@@@@@AA@@A@@@A@@AA@@@@@A@@@@@A@@@AA@@@@@A@@A@@A@@@A@@@@AA@@@A@@@@@A@@@AA@@@A@@@AB@@A@@@@A@@A@@A@@@@@A@@@@AA@@@@@@@A@@@@@@@A@@@@@A@@@@A@@@@A@@@@@A@@@@@@@A@@B@@A@@@@@AB@@@@@BA@@@@BA@@@@@@BA@@@@B@@@@AB@@@@@@AB@@@@@@A@@A@@A@@@A@@A@@A@@@@@AA@@A@@@@@AA@@@@A@@@@AA@@@@@AA@@@@A@@@AA@@@@A@@A@@A@@@@@AA@@@@A@@A@@A@@@A@@B@@A@@B@@A@@A@@A@@@@@@@@AA@@@@@@A@A@@@A@@@A@@@A@@@A@@@A@@@@AA@@@A@@A@@A@@AA@GDEFEFCDGBK@CBEBE@E@EAG@ECGCKEEAGCCCAC@A@CACAACAE@EBKHiTKHCFEDGHKDGBEBKDIFKHIJADEBCAE@EAGAI@GAIBGBCBODMFGDE@GBEBCBCFCLABADEBE@C@CBEDCHAHERAJCHCLADAHADEJEFAJAJ@N@H@FBJBJBHDJDD@HBH@D@FAFABCBC@OBEBOBC@C@EDKBGBKDIBCBC@@@CBA@CD@@CDAB@BCB@@A@@BA@@@@@A@@@@@@@A@@@@@@@@@A@A@@@C@A@AAAAAACA@@CA@@A@@@A@CB@@A@CBA@A@A@C@A@C@A@CAA@A@A@A@ABA@ABABCB@@@@@@ABCBEFGHCDGDKDGD@AAAAC@C@BC@A@A@A@@@@@BC@A@A@E@C@G@A@C@C@ABCBCBA@AD@REVETCFABA@@@AG[ACAAAACAICCCIGA@AAA@@@C@A@A@@@A@@@@@A@@C@@A@CA@@CA@@I@E@@@@@A@@@A@@@A@@@@@AACABI@@@AGAC@@AGA@@C@@@@C@@B@@A@@@@BCKACA@AIA@@@@@@E@AF@JAFCDELCDAFEFEFCBA@A@@@A@A@A@A@@@A@A@@A@@@A@@@@@A@@AA@@@A@@@A@@@A@@@@@A@@@A@@@A@@@A@@@A@@@@AA@@@A@@@AA@@@@A@@@AA@@A@@@@AA@@A@AA@@A@@AA@@BA@A@@@A@@@AB@@@B@@AB@@@BA@@BA@@@ABA@@@A@@@A@A@@@AB@@A@A@@@A@@@A@A@@@A@A@@@A@@@A@A@@@A@@@@BA@@B@@@BA@B@@B@@@BB@@B@@@BB@@B@B@@@B@@BB@@@B@@@B@@@B@B@@@@@B@BA@@@@B@@@B@@@B@@@B@@A@@B@@@B@@@B@@A@AB@@A@@@A@AA@@A@A@@@AA@@A@A@@BA@@@A@A@@@A@@BA@@@A@@B@@A@@@AB@@A@@@A@@B@@A@@@AB@@A@@@AB@@@@A@A@@@A@@@A@@@A@@@@@A@A@@B@@A@@@A@@@@@AB@B@@@B@@AB@@@B@@AB@BA@@BA@@@@@AB@@A@@BA@@@A@@@A@A@@@A@@BA@A@@@A@@@A@@@A@@@A@@@AB@@A@@@@B@@AB@@@B@@@BA@@B@@@@@BA@@B@@@BA@@B@@AB@@BB@@@B@BAB@@@B@@FB@@@@@B@@B@@B@@@B@@@B@@BB@@@@@B@@@@A@@B@@@@@@@@AB@@@@@B@@@@@@@B@@@@@BB@@B@@@B@@@@B@@@B@@@BB@@B@@@B@B@@@B@@@B@@@@@B@@@@@B@@@B@@@@@B@@@B@@@@@B@@@@@B@@@B@@@@@B@@@B@@@@A@@@@@@@AB@@@@@@AB@@@@@B@@@@@BA@@@BB@@@@@@@BB@@@@@@BB@@@BB@@@@B@@B@@B@@@@BB@@@@@BB@@@@BB@@@@B@@B@@B@@B@@B@@@BA@@B@@@@@B@@@B@@@@@B@@@B@@@@AB@@@B@@@@@B@@@B@@@B@@@@@@BB@@B@@@B@@@B@@@B@@B@@@B@@@@@@@B@@A@@@@B@@A@@@@@@@AB@@@@A@@@AB@@@@A@@@@B@@@@@@@@AB@@@@@B@@@@@@@B@@@@A@@B@@@@@B@@@B@@@@@B@@@B@@B@@B@@@@BB@@B@@@@@@BB@@@@@@B@@BB@@@@@B@@@B@@@@@BA@@B@@@@@B@@@@@B@@AB@@@@@B@@@@@BA@@@@B@@@@@B@@A@@B@@@B@@@@@@AB@@@B@@@@@@@BA@@B@@@@@B@@@BA@@@@B@@@B@@@@AB@@@B@@@@@B@@A@@B@@@B@@@@@BA@@B@@@@@B@@@B@@A@@B@@@B@@@@AB@@@B@@@@@B@@A@@B@@@@@@@BA@@@@B@@@@@@@BA@@B@@@@@@@BA@@@A@C@A@CAE@CAEAEAEACAC@EAE@CAE@AAAB@@@BA@@@@BA@@@@BA@@@AB@@@@@@AB@@@@@BA@@@@@@BA@@@@B@@@B@@@@@B@@@@@@B@@@@B@@B@@@@@BB@@@@@B@@@@BB@@@@@@@BA@@@@B@@A@@@@@A@@BA@@@@@A@@@@@A@@@@@A@@B@@@@A@@B@@@@AB@@@@@@AB@@A@@@A@@@AB@@@@@@@B@@@@@B@@@@AB@@@@@B@@@@@B@@@B@@@@@B@@@@@BA@@@@B@@@@@B@@@@@B@@@@@@@B@@@@@@@B@@@@@@@B@@@@@@@B@@@@@@@B@@@@@@@B@@@@@B@@@@@@@B@@@B@@@@@BB@@@@B@@@B@@@@@B@@@@BB@@@@@B@@@B@@@@@BB@@B@@@@@B@@@@@B@@BB@@@@@B@@@B@@@@@BB@B@@@B@@@@@B@@@B@@@@@B@@@BA@@B@@@@@B@@@B@@@@@B@@@B@@@B@@B@@B@@@@@BB@@B@@@BB@@B@@@@@BB@@B@@@B@@@B@@@B@@BB@@@B@B@@@B@@@@@B@@@BB@@@@B@@@B@@@B@@B@@B@@@B@@@@@B@@@B@@B@@B@@@B@@@B@@@@@B@@@B@B@@@B@@@BB@@B@@@B@@@B@@@B@@@B@B@@@B@@@B@@@B@@@B@BB@@B@@@B@@@B@@@B@@@B@@BB@@@B@@@BB@@B@@@B@@BB@@@@@BB@@@@@@AB@@@B@@A@@B@@A@@B@@@@@B@@@@@@BB@@@BB@@@@@@BB@@@@BB@@@@B@@B@@@@BB@@@B@@B@@B@@@@@@B@@@@@@@@@B@@@@AB@@@@B@@B@@@BB@@@@B@@B@@@@@BB@@B@"],"encodeOffsets":[[120907,34992]]}}],"UTF8Encoding":true}