{"type":"FeatureCollection","features":[{"type":"Feature","id":"441203","properties":{"name":"鼎湖区","cp":[112.565249,23.155822],"childNum":1},"geometry":{"type":"Polygon","coordinates":["@@BA@G@@BABB@@B@B@@AACC@AAC@CA@A@E@EACAC@ABAD@DAD@B@@@B@@E@@@AAC@C@CDGBEBGAK@GBEHGGKEGEGEEBG@A@CCAGACCEAC@G@C@E@CAAACC@@CACAA@ACCEAACAA@CA@AAEC@CACAAEACAAACACCACCEAGEGEECKAEAGAEBEAC@EBC@E@E@CBEBCDCDG@EBGBGDGFGBC@E@C@C@GECEEAE@C@EBAB@DBJBJBFCLAHK@C@CDEDCBCDGDEBABKB@ACECEAEEECACECEACACACACEGEGCAACGEA@EFCJADAFAD@@@BCDA@ABC@A@C@A@ABADED@@@@@@@@AB@@A@AB@@A@CBDDGFBBJJGFC@ABADA@DJBDBBB@@D@DIFADADBHA@@BA@A@AA@@@BAAA@CB@@ABA@A@C@AD@B@BB@@BAB@BADABBDBDAFC@AB@B@BADAB@BC@C@ABC@C@CBABADA@CBCDABBBAD@B@DC@AD@B@DAB@D@BCDBB@FBBABAB@BAF@DCBA@A@AB@@C@A@@D@F@DAFCBA@A@AB@BADABCB@B@DAD@B@DAD@B@BDBD@B@@D@BABAD@DBBADCBABCD@BBBBBDB@B@BDBD@DCD@DBBBBBBB@DD@BADBBDFBBABDD@AD@FCBA@FFBBBBDAB@B@B@BBDBDB@B@BBDD@BBBHDDB@DBB@BBB@BDBBBBD@@ABAD@@AB@@@BAFANF@@B@@@B@JG@@DCNA@ADAFGHEJAJBD@FB@@BABADCJC@CHI@ADABCAE@AHALALAB@@@D@BBD@DBDBDBBBDDDBDBFBFBFBDBBBDBDDDBDBDB@@DAHCBBFDB@DBF@DDFBDDBDB@DBB@B@B@HEH@HBHCJABBD@B@DCHBHAJEHANIDADEDKAGAEDCACAC@C@EBADCF@DADEBCAG@GECCAEACI@EDGACBC@EFEHGDJ@@BD@BB@BBDGF@DDHBDD@B@DBBDBDBF@BCDABB@D@D@@@DBBB@BA@C@AD@BCBCDAD@H@DADC"],"encodeOffsets":[[115476,23781]]}}],"UTF8Encoding":true}