{"type":"FeatureCollection","features":[{"type":"Feature","id":"140603","properties":{"name":"平鲁区","cp":[112.295227,39.515603],"childNum":1},"geometry":{"type":"Polygon","coordinates":["@@F@HIBIHOHW@ICGIGGCYISGAGDELARCTAHQDOFGFCDEDOTMPFL@N@X@XDV@J@LAFAPCNE@KEIEICKHQRULOFQF[PIVAdDZFTFLBNALCDCDCJONQNMJMHQAMCICGBAECGAOCKCQSMMICQFMDKCO@@BGHIDKDC@AAOMCGCGICECDG@ACAIAWGUEEBENCBKFCBADEREJABC@UEIDC@CAIAQICCCGQCGAQCI@OBKDOFMBQASNODKCGAG@GBGBE@EACCC@C@A@G@G@E@EC@CBADCBACCEEGCG@EAI@O@GAI@AAAABADADABCCEIACBEACAGAIAG@GBA@E@C@GAEAKACDCDAFADEBCB@B@BAB@BA@@B@BABABAB@@ABC@C@CAA@AAAAAAA@A@A@CAC@E@E@GBCDADCHCFEDIJEBMBOAQ@EDIDGBECUWQKIBCBE@EAEGACECC@GACECEAG@E@EAMGCGGECE@CACAACEKAGCAE@GAG@E@CA@CAGAAAAECEAEAE@EFGFQLABGDEBE@IAI@CBC@@C@CCAWDA@AFCDABEFMLADCBABBF@@DFBFBHBF@FADADCHEBEBEBAF@H@FEFEFEFCLAHBJADC@C@C@CEEACBIDEBOJIJCDQFC@I@MGEAE@ABCD@BKBCHEJEPGPINCFAF@DBHBJJHHDNDPF\\BTFV@\\ATBT@PFNRKJGHMNILIJGFOHOHMJML@@CJAHALAHEHCDEDD@DFBFBDDD@D@B@DADCBEBCB@FFDDDBFBBBFCBADCFEDCDCDADAF@BABBDBDFD@@DB@BDDDBFDDBBDDDDBDBD@FBDBDBBBBDDDBDTdBDA@AD@BABADAB@DAD@DBF@HBDBF@@BD@B@D@DAD@DAD@DBB@D@DBBBBBBBNA@@B@DAF@DAD@DAD@FBF@D@D@DBB@DBB@BFBFBDD@@D@BBFDFD@DBBFDDDDBFDDDDDJDBDHHBBDDBDBDBDDFDBDDBDDDBBBB@B@@JHDB@BBFBDBD@BBF@D@BBDBBBDB\\B@BBBBB@@BBDDH@@@BBD@BDBBB@BD@BBFDB@DBFBDDDBDDDDBDBB@BDD@BBDBD@BBD@BBB@B@BBFBDDDBBBDBDDFBBBD@BBFDDBBBBBBDB@@DDHJDDDDBDDDDBBDDD@@FCLIFCJSVITAVCJC@GAIAECGQU@KFIJAJANCLCJWFOTYVMNCVCHABC@EAGISJKNBLDL@HCD@LIPWFEJ@L@FBVDXDLCHEDEBEAEEQIKAI@EDEFCHCPINMHIFGDGTON@LCJAFCDGACEKJOHCFAJDJDF@@EBEHOFMFIHCNETD\\CPE"],"encodeOffsets":[[115149,40646]]}}],"UTF8Encoding":true}