{"type":"FeatureCollection","features":[{"type":"Feature","id":"350629","properties":{"name":"华安县","cp":[117.53631,25.001416],"childNum":1},"geometry":{"type":"Polygon","coordinates":["@@FE@C@GAIAG@EFEFAFDF@J@FCBCCC@@@ADCFE@@FCFCJ@NCDGJEJAL@HAFC@@@A@ICGBELSJHDADE@CBCD@F@L@D@H@JCDAD@DA@@FADCDCBA@KAKBK@ODMHGJGJEP@HEJKHID@BDFHLHF@DCFI@I@KFGBEBCGICEBAJCNEBE@IACCAAA@@@@GCOIGACEAIAIACE@GBG@E@CAAAEEAEBCACCCCAEAE@ABCDADCDEBADA@ABC@A@A@AAA@AAC@E@C@C@A@C@@A@A@A@A@C@A@AAABA@ABC@A@A@AAAA@A@AAA@AAAAA@AAA@AAA@AAAA@AA@GCSGQEIGIOII@KFM@IHEPCP@H@DC@A@C@GAGCCCCCEACECEAECAA@E@C@EDI@EACBEDCDABADE@EBA@EBCBCBC@E@GBACKQICI@A@CCAE@ECGCAAAEDAFABABADA@ABA@AB@D@DADCBC@@@@DKBKCIAIEKHKFE@@B@@@FGJQDIFILMB@JKJIJIRDPAFADSFMJIECWEIGCIDIHGFDTHDBBADABABCBA@@CUAKDSB@JNJDDFDBBBDAB@BC@CDC@KAA@@AAAACACACACA@@@ELIFIDG@CGCA@AAGAAAC@C@CBCBCBAFAFCDCBCBE@C@C@CACC@@ECGCC@E@E@EBCBCBCDCDAFABIDAA@@CAC@EBCBAD@H@D@BBDBBBD@F@D@F@DAFCN@F@BBD@@@@@BDJGHGBQ@AAAACCCCCCCACCCEEAAACCEAGCAACACAACAACAACCEACCCCACCCAACEACCCAA@CBABADCAEAE@A@C@CBCDABCDA@EAA@C@EBC@EAA@C@E@EBCBEBCBADAFADAB@BBBBDBBAF@DADBB@BBFD@BBBBBDBB@DB@DBF@B@@BADAD@B@D@BBBBD@D@DADADCDABADABA@CAC@ABADAD@DABADCBC@C@CAC@C@GCMGWBUHQDEF@N@L@B@D@DABADAFADADADABCBCBABC@C@E@E@CBC@A@@@MDGHCBCBA@@@C@A@@AAAAAAACAA@AA@ACAABBB@BAB@B@BBDBB@B@B@BC@ABBBBBBBBB@B@BABABBBBBBBBB@@@B@BABAB@D@B@B@BAB@B@DAB@B@B@BABABADBB@BBB@B@BAB@B@@CBA@C@CBEDABCFCFEDABCBCBEBCBCBCBCDADADADAF@FAD@DCD@DADABAAAACACCCAEAE@CBC@CBABADCDC@ABC@ABCBCDAF@D@D@F@BA@ADCDCBCD@D@F@DBF@BDD@@FDLDN@FDALERILOFUFM@MEI@CDCFB@DDF@FDDBDDFFDDDDDDDBDDDDBB@B@B@B@D@BBB@@BBBBB@@BB@B@BBB@B@BBB@@B@@BDBDPFLBLHPCLENCD@D@FBD@BDBBBDBBFDBBLFHCLCP@VAPADBFCHELMNMHCL@RARBJAT@HBJFFRC^@PC\\ATBNJJFPHJFN@RBPBLDfBBIVEPYNQJEF@HJNBR@R@P@JDDDAJADB@D@HBDBBPDL@JAHDLHHHBR@HFFBBDCHILED@BFEL@FCF@FBDB@D@B@F@D@B@"],"encodeOffsets":[[120377,25817]]}}],"UTF8Encoding":true}