{"type":"FeatureCollection","features":[{"type":"Feature","id":"520626","properties":{"name":"德江县","cp":[108.117317,28.26094],"childNum":1},"geometry":{"type":"Polygon","coordinates":["@@@@HAD@BABA@ABA@CB@DAB@DBBDBBB@B@@DBBBBFADAD@DBDBDBDDDDDDDDDDBBB@BAB@B@@B@D@B@D@B@BBBBBB@B@BAB@BA@@@@BA@@DFBRBPBRBV@PAPEL@HBNDJDL@LARCXA~JhPX|@XELFEFCDEPDDNCLDJ@FAXEPAFBJDJDHALKZSF@FBBJFJ@JCHQJMHUBSVCDFHLRCRDPPPJ@JGHCJ@LBDBB@BBDBHB@ADGAGACGEE@A@E@M@OAEACCBKB@FDBDJBH@LCFADABI@GDCFCDCFEDGD@F@DA@ACCKCKAECEGAIDCD@FBH@FMFGHIHEHAHBDHDHFHFJHLHRHNFNHLDLBLEFCFGDGFGBEBAFHHHNDHBJBH@JCJEFEJGJ@LDJFHJFLFHFDF@L@JCHKLGJKFGBIFEFCHDFDDFHJFCFEJEHGJAJ@HHHLFFFB@@@BBBDFFBD@@B@BBBBBBB@@@BBB@BBB@DB@@D@@BB@B@@BB@FBDBB@FBB@BB@F@@BB@D@@B@@@B@B@@ABA@@BA@AB@@AB@@AB@@@B@B@@@B@B@DB@@B@BB@@D@@@BBB@@BB@B@B@BBB@@@B@@BB@B@@BB@@@B@B@@BB@DB@BB@BB@@BBB@BB@@B@@B@@BB@@@@B@AA@A@@@A@@AA@@@@@A@@@AAA@@AA@@@AA@AA@AAA@@AA@AA@@@@AA@@AAA@@AA@@AA@@@A@A@A@@A@@A@@@AAA@@@A@@AA@@B@@@BAB@B@B@B@B@B@B@B@DBD@B@@AHADAHEFCBCDEFGBABCBEBCDGBCBEBEBCDCHEDCH@F@D@DBD@F@FBDCDA@CCCGCCCAE@EBEBEBGDEDEBEBC@E@EBC@C@CDEDEBCDCDCBCBCBEDE@CGIGQEMOWCGGOCEB@RGFEDG@IBCNBPBBC@KAIAE@CAI@EAIBCDGFAD@DAFCDADEDEBABC@C@EAE@EBCDCH@FFBHBJFBHAHCF@HDLDNBNDJ@J@JBF@BACAEECEBCNIPIPGNELGLGHCJGDCBCBE@GACAIAKEAE@IAE@M@E@GAE@E@CEFEBK@IAC@GDGHGJGDEBGBKBIJGJELEFCBA@ADABAF@D@HBF@F@HAF@D@F@H@HBDBF@F@DBF@FADAD@HCDADABABCBEBEDEDEDCDCFCFABADAFAFCDECECACACECEACAECCCGAECEACAECGCIACCICAECCCEAC@EAIAKCCCGMIMGOEIGOEICECIEECCIGCAAEC@CCAEDG@EBI@K@ECGAA@AA@@@@A@@@@AACC@@A@@@@AA@@@@@A@@@A@@AA@@@A@@AA@@@@@A@A@A@AA@@A@@@A@@@@@AA@@A@@@@@A@AA@@C@@@@D@@@BA@@B@@@B@@@BA@@B@B@B@B@@AD@D@B@BAB@@@B@@@@@BCB@@S@EAECECCACCCCECECG@G@C@CBCBIBG@C@C@CBEBC@EDEBED@D@PDJDNABC@EBGAIAEBCJAJ@FDNBL@HBJ@FDL@H@DEBK@I@IFIBICGGCGAGCICGAEBGAMBKFK@EAAK@EBK@GAA@GDIBGDALCHGFEBI@K@GBGCACIGEIACC@C@EAAC@GACACEGECCCCCGECAECEEGCGECCCACCCACCCACCIAC@E@IAEBGACBG@E@I@C@EAC@EAKAK@GCKCKAOEMAOCGABGBEDEDEDKBIAEGEGCMEOAM@EMIPGDIFCDEFCHCHKJGJGJEFINADCNADABCBA@AA@@@A@C@@AE@AAAEAA@A@@B@B@DAB@@A@A@@ECA@ABC@AAA@AEA@A@ABA@AAAECA@@G@AA@GD@@C@AAEAICAACAAA@C@@E@AAAB@@CB@B@D@BABABABAD@B@@BBDF@DADABIBC@CAC@ECA@AAA@C@AB@BAD@DBD@DBH@J@BABADC@ABC@C@CAC@CAGCC@A@A@@BAFGJAAA@CCA@EBBHDDBBB@DHBB@DCF@B@D@DDDDFBF@DBFBFBDDDBF@BBABA@@BBBJ@D@D@D@B@BBD@B@BBH@BBB@B@D@D@BBFDD@BABAD@F@F@D@DBFBH@D@D@D@B@DABCBABBBB@"],"encodeOffsets":[[110391,28860]]}}],"UTF8Encoding":true}