{"type":"FeatureCollection","features":[{"type":"Feature","id":"652828","properties":{"name":"和硕县","cp":[86.864947,42.268863],"childNum":1},"geometry":{"type":"Polygon","coordinates":["@@EJ@\\B\\DV@²@Ţ@tBd@¢@LBBB@@@B@@@B@@AB@B@@@B@BA@@@ABAB@@AB@@A@@BA@@@A@@AA@A@@@@@A@@@A@@@@@@@A@@BB@@@@@AB@@@@@@@B@@@@@@@B@BAB@@@DCB@BA@@@@@A@A@@B@@@BAB@BBB@BBDBB@BB@@B@BA@@@@BA@@BA@@B@@@@A@@@@@A@@@@@@@@B@@@BAB@B@BA@@BABA@A@@@A@A@@@@@@B@@@D@@@FBD@B@B@B@@@@@B@BA@@@@BABA@@@A@A@AA@@A@@@A@@@@B@BA@@B@@@BABA@AB@@@@@B@DB@@B@BB@@@@@@@@@@@@@B@@@@@@@@@BA@@@CBA@@BA@@@A@@@@@@@@@A@@@@B@@AB@@A@@B@@@@@B@@A@@@B@@B@@@B@@@@@B@@BB@@BB@@@@BB@@@@@B@@@@BBB@B@@@@B@@B@@@@BAB@@@@BBDB@@B@@@@@@@@@AA@A@@@@BA@@B@@@@@@@BA@@@@B@B@@@B@@@@AB@@@@@@A@A@A@@@A@@@A@@@A@@AA@@B@BA@@BA@@@A@@@@@ABG@AD@DDB@AB@@@@@@@@@@@B@@@@ABA@@@@BAB@D@@A@@@B@BBBB@@B@@@BBB@@@BB@AB@B@@@B@@@@@B@@B@@BB@@@@@@B@@B@@@@@@A@@@@B@@@@@@@@@B@@@@@@A@@@A@@@@@@@C@A@C@A@@@A@A@@@@@AB@@@@AB@@@@@@@@DD@B@@@@@B@@@@B@@@B@@BB@@@@B@@@B@@@@AB@@@@@@@BA@@@B@@B@@B@@@@@B@@@@@@@B@@B@@B@@@@@B@@@@@@@@@BB@@@@@@@@@A@@@C@A@@@A@@B@BA@@@@@@B@@@@A@A@@@@BA@@BAB@@@@@BA@@BAB@B@@A@@B@@@B@@AB@BA@@B@@@DAB@B@BAB@B@BA@@B@@@@@B@BAB@BAB@@@@@@A@@B@@AB@@@B@@AB@@@@@BA@@B@@@B@@AB@@AB@@@@CAA@A@AAC@@@@@@A@ABA@@@A@A@@B@@@@@B@@AB@@A@@B@BAB@@@BAB@@A@@@A@@@@@ABA@@@@@A@A@A@AB@@AB@@ABA@@@E@A@AA@@AAAA@AA@@A@@@@B@@ABABA@@@A@@@A@CBA@A@@@@@@@BB@@@B@B@B@B@BAB@B@BAB@@A@@B@@@@@@@@A@B@@@@@@@@AB@@B@@@@@B@@@@@B@B@@@BA@@B@@@@@B@@@@@@@BA@@B@@@@@@@@@@B@@B@@@@@B@@@@@BAB@BAB@B@B@@@@AB@@@@A@@@@@@@A@@@@@A@@@@@AB@@@@A@A@@@ABA@@B@@@D@BAB@@@B@BAB@BA@ABCB@DAB@BAD@BAH@@@BA@@@BB@@@@@@@BAB@@@@@B@@@@BA@@@@B@@B@@@B@B@@BB@B@B@BA@@B@@@B@B@B@B@@@B@B@@@B@@@B@@@@AB@@@@@@BB@B@B@BAB@B@B@@@@@BAB@BA@ABABA@ABAB@@AB@B@@AB@B@@@B@@@DAB@B@B@D@B@B@@@@@B@B@BA@@@ABB@@B@B@@A@@B@@@@@FAB@B@DA@@DCD@BABAB@B@D@B@D@D@D@F@@@BBDBDBDBBBDB@@@@@B@B@@@@@@@BB@@@@B@B@D@B@B@@@B@@BB@BAB@@@BA@@B@@@@IL@@AB@@@@EHA@@@@@@@AB@@@@A@C@@@A@AB@@@@AB@@A@@@ABAB@@C@@@AB@B@@@@@@B@@BA@@@@@@@@@@@@B@B@BA@@B@@@B@@@B@@@@@B@B@@@@A@@DAB@@@@@@AB@B@@ABA@A@CAA@C@EBAAE@CAC@ED@DB@BDFB@@BBBD@@@BAF@BABC@A@CCBEA@C@ABEDEDKDA@@B@@AB@@@@B@DBBB@BEB@D@@D@BBDBHD@BHC@ABABCBADADDFLABECC@C@CBAB@DBBB@B@D@B@B@BAD@@DBBBBA@G@A@AB@D@B@B@@A@C@@AA@AAA@A@A@A@AAA@@@@BB@@BAB@B@B@BBBB@@BAB@ACAAAC@@A@EAA@@C@A@EBC@EBG@GAE@CA@@A@@C@K@A@@A@@A@@@@BA@@B@@ADCDA@@BA@A@A@ACACBABEA@ABADA@AA@A@@@A@@@@@@@@@@@@C@@@@@@A@@A@@A@@@B@BEACCC@@AAA@ABCB@B@@@B@BBB@@BD@@@B@B@B@@@@@B@FDHBHDF@DDTDR@HBZBR@L@H@FALAlEVMZWNmBIB[VmACAG@C@q@EBC@QBCBEBSDGDKDGBMDUCQGG@IDIFEDA@CDSJEDE@DB@BCBKBA@KVIVKFMHEBC@GAECGC@@A@EB@BA@AAG@ABA@@BAD@BE@E@G@C@ABBDABA@ECA@C@C@EBGBQ@MBA@ABABADCBGBGDGBE@CAA@AA@@A@@A@@@@@@@A@@@@A@A@@BA@@@AB@@A@A@@@A@@@ABA@@@A@@@@@@@A@@@A@@@A@ABA@@@A@A@@@@@A@@@@@A@A@A@A@@@@@A@@BA@@@A@A@@@@@A@@@@@B@@@A@@@@@AB@@@@@AA@@@A@@@A@@@A@@BA@@@A@@@AB@@A@A@A@A@A@AA@@A@A@A@A@@@A@A@@@A@A@@B@@A@A@C@@@A@@BA@@@A@A@@@A@A@@@A@AB@@A@A@A@@@A@A@ABA@@@A@@B@@A@A@@@ABA@ABAB@@A@@@A@@B@@A@A@A@@@A@@BA@@@A@A@A@A@A@A@@@AB@@A@@@A@A@A@@@A@A@@@A@AB@@ABA@@BA@@@A@@@@BA@@@@@A@@@A@@BA@ABA@A@@@A@AA@@@@@@@BA@@@AB@@A@@@@B@@A@A@@B@@AB@@@@A@@@@@@BA@AB@@ABA@@@A@A@@BA@ABA@AB@@ABA@ABA@@@A@A@A@@BA@A@@BABA@@BA@A@@@A@@BA@A@A@@@A@A@ABA@AB@@A@@@A@@BA@@@A@C@@@@@AA@@@@A@A@@@@@A@@@@@A@@BA@@@A@ABA@@@ABA@@@C@@@AA@@AAA@@A@AAA@@A@A@@@@@AAA@A@AAA@A@C@C@A@ABGH[\\IJADA@QP[XWTIJ@NBPE@@@S@W@[FIBG@A@A@A@AA@@A@@@A@A@@@@AA@AAA@@@@@@@A@@@@@@@A@@@@@@@@BA@@@@@A@BB@@@@B@@@@@BB@@@@@@@BA@@BA@A@@@A@A@@@A@ABA@A@@@@B@@A@@B@@@B@@@@BB@B@@@@@BA@@@@B@@@B@@A@@@AB@@A@A@@@A@@@@A@@@A@@A@@@@BA@@@@@@BA@@@@@@@@@@@@@@@A@@@@@@@@@@@@@@@@@AB@@@@A@@@@@@@@@@@@BA@@@@A@@@@@@@A@@@@@AA@@@@A@@@@@@@A@@@@@@@A@@A@@A@@@@@@A@@AA@A@@BA@A@@@@@A@AA@@A@@@A@@BA@@@AB@@@@@@A@A@@A@@@@A@@@A@A@C@C@ABA@C@A@A@AB@AA@@BEBA@C@ABA@@BA@@AA@AB@AA@A@@@@J@Z@b@^@ZA@MBABCBOL@@A@@@@@B@@@BBDBDBDBBBB@BBD@FDBBBBDBDBDBBBFBBBDBDB@BBBDBBB@@BBBBB@BDHFFFBBBB@@B@@@@@BB@@@@FDBB@@B@@@@BB@BBDB@@@@@BB@@BBBB@@B@@BB@@@B@@@B@@@@B@@AB@@@@@@@@@@BB@@@@@@@@@BB@@@@@BB@DBBBBBB@BBBBB@B@@@BB@@BBB@BBBBD@@BB@BBBBB@@@BBBBB@@B@@@@BBDD@@BBB@@BB@@B@@BB@@BBBDBBB@@@@B@@@@@@@@@B@@BB@@BD@B@BBD@@BB@BB@@B@@@B@@BBBB@@@BB@@B@@@BB@DDDDFB@B@@@@@@B@@B@@@@B@@@@B@@@@BB@@@@@@@@B@@@@@BB@@BB@BB@@@@BDB@BB@@BB@BB@@BBBBBB@@@BBB@@BBDB@@@B@@@B@B@@BB@@@D@BBD@@@D@B@BBB@@@@B@@@@@B@BABA@@D@DAB@B@DAD@DAF@DAB@BBB@BB@@B@B@B@BBB@BBBBBBB@BBB@@@B@B@@@BAB@@@B@BAB@B@B@D@B@FAB@B@DBD@D@B@B@D@H@F@F@B@@@D@B@B@B@@@D@DAD@B@B@B@B@B@@@@@AB@B@@@BB@@B@@@@@@@B@@@@@BA@@@@B@@@B@@@@@B@@AB@@@@@BB@@@@@@B@@@@BBB@@B@@@@@@@@@B@@@@@@@B@@@B@@@@@@@@@B@@@@@B@@@B@@A@@@@@AB@@@@@@AB@@@@@@BB@BB@B@@BBBB@BBB@@@@B@@B@@B@@@@@B@@@B@@B@@BB@@@@@B@@@@@B@@@@@@B@@@@B@BBBBB@B@@@B@@@@BB@@@B@@B@@B@@@@@B@@BB@@@@@BB@@B@@@@BB@@@B@BBB@B@BBB@@B@@@@@@@@@@B@@BB@@@@BB@@@B@B@@@@B@@A@@B@@@@@@B@@@B@@@@BB@B@@@@@BAB@B@@@B@@@DBB@BBBA@@B@BB@@B@BAD@B@@@B@@@@@B@B@@@@BB@@BB@@BB@@@B@@@@@B@B@@@@@BB@@@B@@B@@@@@BA@@@@@@B@@@@B@@BB@@B@@ABA@@B@@@DA@@B@B@B@B@@@B@B@BA@@B@@A@@@@@A@@BBB@@@BA@@B@DABAB@BA@@@@FA@@@AB@@@@A@AB@@@@A@@A@AA@@@@@AB@@A@@@A@@BAB@@A@@@@@A@@@@BA@@@@@@@@@@AA@@@@@AA@@@A@@@@@@A@@@@A@@@@@@A@@@@AA@@AA@AB@@A@@@A@@@@@AB@@A@@A@@A@@@@A@AA@@@@AA@@@@@@@@@@@AA@@@@@@@@@@A@@B@@@@A@@@@@@@AA@@@@@@@@@@@AA@@@@A@@A@@@@@@@@AB@@@@@@A@@@@@@@A@@@@@@@A@@@@A@A@@@A@@@A@@@@@@B@B@@@@@B@@@@BB@@A@@B@@AD@@@B@B@BBD@@BB@B@B@@@B@@@D@D@B@DBB@D@B@B@BABBB@B@B@@@B@@BB@@@B@D@B@B@B@@@B@@@B@B@B@@@B@B@BBB@B@@@BBB@B@B@B@D@B@B@B@@@@@B@B@B@DBD@H@F@FBD@D@B@D@DBB@BB@D@@AB@D@@BBD@D@@ADCB@DAB@D@FBB@BD@@BBBBB@BBBFBDB@B@B@BDDDB@BBD@B@@B@B@DALAB@BKDEDCBEBA@ABADA@ABG@@@CDENEFA@CBGD@@@@A@@@@B@@@@@BB@@@@@@@DDBBADADAB@@A@@@@@@B@@A@@B@@@@@B@B@@@@AB@BA@@@C@A@A@@BA@A@@BA@A@@BA@@@@@A@BB@@@B@BB@@@BB@@@BAB@@@@ABADA@@DA@@B@@AB@@@B@B@@A@A@@BA@@@A@A@ABA@AB@@A@@BA@A@A@@@ABAB@@@BA@@@BBB@@BDB@@@BB@@B@B@B@B@B@@@@@@@@A@ABA@A@A@A@@BA@A@@@@@@@@@@B@B@@@BAB@@BB@@@@@B@@@@A@@@@BA@@B@@A@@@AB@@@B@@ABA@@@@BA@@@@B@@@D@B@BAB@@@BA@@B@@A@@BA@A@@BAB@BAB@@@B@@AB@@@@ABB@@BB@@B@@BBB@@@BB@@BB@@B@@B@B@B@B@@ABABA@@BA@@@@B@B@@@BA@@B@@@@@BB@@B@BB@BB@B@@@B@B@BBB@@@BBB@@BB@@@@BBB@@BB@@@B@@BB@BBDBBBD@BBBB@@BB@@BBBBB@BBD@BBD@B@B@BAB@D@@@B@B@B@B@@@BB@AB@B@BBB@@@BB@BBB@BB@@BBBB@@B@B@D@@@B@@@@@B@@@B@@A@@BA@@@@@AB@@@BA@@@@@A@@@@@@@@B@@A@@B@@A@A@@@A@A@@@A@@@@AA@@@A@@@A@@AA@@B@@@BAB@@ABCB@BCB@@A@ABA@AB@@ABA@AB@@@@BB@BBB@BB@@B@D@B@B@@@D@@@BA@A@A@AB@@A@@@@BAB@B@@BB@@BB@@@B@@BBBBBB@B@@AB@@@@@@@BA@@BAB@B@B@@@@BB@@@BB@@@@BB@@@@@@@BB@B@@B@@@@@BAB@B@DAD@B@BAB@B@B@BAD@DBD@B@D@B@B@@@LDBB@JBDFDBB@D@DDJBL@L@FEHEJANIJAD@DDDTPHBD@D@D@F@R@L@FAHAPAFAJ@NANCH@FBFD@@DHBBD@NBFANENCPCD@HDJBH@J@J@@@HBPBB@BBHJV\\DBFDBBDBD@HCNCBAJGLIBA@EFGB@D@D@B@HAB@BBFFNDB@@@HBBB@DB@@JAD@BPJDBH@J@F@HDFFLBD@FAD@J@H@DANGB@@@BBDBF@HAFEJCH@L@F@H@NBB@DBNHJ@D@BAFAFAHAPBRFBBFDDH@HCJB@FDHBF@JANGB@JGB@TB`ABFPTFJBBBA^CNCF@HDHBFAHAXC@GRIVGTGLALBL@HAHCLAD@HBDBHDJ@F@HEJEDAD@JAJAJ@NALAJBJBB@F@VAHAF@LCPCHCTCFBFBHBHFB@FBD@B@D@JE@@B@D@JDLBFATEB@VCX@XDVHDBD@F@BBB@DAB@FCN@NCD@F@D@HB^FB@B@AACEAAB@DABA@@@@@@BC@E@ABATOPKDCBA@C@CBCHAHAFADC@EBCDELADCBC@@BAHCDCJEDEHMBE@C@AAABEAEAKAG@@@@@A@EDIFIDA@ADAHADAJBB@J@LAFADCHIBI@AAI@A@@B@N@H@TDJBPBFBBAB@BAHIB@HIBAHELCHCB@HAFCHIBGDA@@BAHEDAHAD@PAFANENIBAHAF@FCHEDANEPENAVETCPAJCLINCBARKTQB@HOFOBKBC@@EI@A@@B@BAPBFAD@DGBEBA@AB@HEDCHCBA@@@A@@AGACAIEMCE@AAGAGCCQG@@EBA@C@A@@A@ABCDABCDE@C@E@CDC@AEEEG@@A@EAIAKAECEAEA@@CCAAC@C@E@AA@@ACCI@@@ADCFEFC@C@@@ECCGECGCGAE@CA@E@E@@@A@@E@EDE@A@@KG@A@C@AEEKEMGeQsQ£][ECAWYieGCcSOEYOAAGECEAICEICECCC@@ICGEAADKBEBAJEDCAM@EFUHUJaHOhVadi@Aba@@DCBCDC@AJ_DC]Ě£@C@AB@@AB@BA@A@A@AB@@ABA@ABA@AB@BABCBABABC@ABA@AB@AA@ABA@AB@DADAB@B@D@@@BA@@ACBA@A@ABC@CBC@C@AAC@ABCBAB@@A@A@A@CBA@CBC@ADABCBABABCDC@CBA@@BA@@BC@@BAB@B@BABC@@BAD@D@B@BB@@B@@BB@@@@@@@@@B@@@@A@@@@A@@@@A@@A@@CAA@A@@BA@@@A@@A@@@@AB@@@@AB@@@BA@@B@@@@@@A@@@A@ABA@A@A@@@@BAB@@A@@AA@A@C@@@A@A@ABABAFIHKBEDEBCDCBC@CBABA@ABABCLKHEFEBCD@DCLELGJEDCB@FANELED@@@HCZMFCHCFEBADCDEHGDEBCDCDEDABCBADCDCFEDGFCDCBCBAFCDCFGBABC@CBCBE@A@E@ABEBA@EBC@E@E@A@C@A@E@E@G@C@E@E@K@I@C@C@EAE@G@O@GBK@GBG@CA@@AAAACAGAABA@C@AAA@AA@AA@CACCIAA@C@A@AB@BA@@@A@C@C@@@ABABA@A@A@ABABABCBEDCBEFEBCFC@AAC@@@AAAAAAAAC@AACAAACAAAAAA@@@CBA@CAAAA@C@A@A@A@@AC@AAA@@BCDGBEBABC@A@CBC@A@A@A@E@@BAB@@AB@@AAA@AA@A@@A@@@@A@@@@@@@@@BA@@@@@@BABA@@@A@@@A@@@A@@A@@@@A@@@@@@@@@@@A@@@@B@@A@@@@@@@@@A@@A@@@AC@AA@@@@@@A@@@@@@@@@@@@@@A@@@@@A@@B@@@AA@@@@@@A@@@@@A@@@@@A@@A@@@A@AA@@@@A@@@@@A@@A@@@A@@@@A@@@@@A@A@A@ABA@A@AA@@A@@AB@BAD@@A@@@AA@AAEACAGAA@CAA@CAA@CAAAA@AAC@AAA@@AAA@ABA@A@@BAB@@@B@B@B@@AB@BA@@@A@@BA@@@@B@B@DA@@BA@AB@@A@A@A@@A@A@@A@@A@@A@@@A@@@A@@@A@@@@@A@@@@A@@@CBA@A@A@A@AA@@@@@CBA@A@@@@@A@@A@@@@@A@@A@A@AA@@@@@A@@@A@A@A@@@@@@@A@@@@@CACAC@CAAA@@@@@A@@@@@@@A@@@A@@AAGAEA@@GECAA@CA@@A@@@A@C@A@@@EAAAA@AAA@A@@@A@AB@B@@@@A@@@AB@@@@A@@@ABA@@@@@A@A@@@@@@B@@@B@@@B@@@@AB@@A@@@CB@@A@A@C@A@@@@A@AAA@@@AA@A@@@AA@@A@@@AB@@@@@@A@@@A@@@A@@@A@@@A@@@A@AA@@A@A@@A@@@AA@A@@@A@A@A@@AA@@@A@@@C@A@@@@AAA@AAACGACACACAAAAAA@AB@@AA@@@C@A@EAA@CAA@@@OBWBo@aKcGKKSKUCaDUDY@_A]@SAQDSHYHSDOPGFMPGJQJ]F_HeHUD@@A@@@A@@@@B@@A@@@@@@B@@A@@@A@@@A@@@AAA@@BA@@@A@AB@@@@@B@@@@AB@@A@@@@BA@C@A@AA@BA@A@A@A@@@A@@@A@@@@@A@@@@@A@@@A@@@A@@@A@@@A@AA@@A@@@A@AA@@@@A@A@@AA@@@A@@@@AA@@@A@A@@@@@@@A@A@@@@@A@@A@@AB@@A@A@@AA@A@@@A@@@@B@@A@ABA@@@@@ABA@@@@@A@AB@@@@@@@@@@A@@@A@@@A@@@A@@@A@@BA@@@@@A@@@@@A@@@@@A@@@A@A@A@@AA@A@A@A@A@C@@@ABC@A@A@@BA@@@A@ABA@@@A@@@@@@@AB@@A@@@@@A@A@@@A@@@A@@@A@A@A@A@@@A@A@@BA@@@AD@@@@@B@@@B@@@@@@B@@@@B@@@@@@@B@B@@A@@B@@A@@B@B@@A@@@ABA@@@A@A@@@C@@@A@A@A@@@A@A@A@@@@@A@@B@@@@@B@@@@@@A@@@@@@@ABA@@@AB@@A@@@A@A@C@@@@@AA@@@@AAA@AAA@A@A@@@A@A@@@A@@@A@@@C@@@@@A@@@CA@@@@A@A@AA@@@@A@@@A@@@@AA@@@@@A@@@@@AB@@A@GBKBGBCFADABCDEBC@C@C@C@UEA@C@MDA@MCE@CBABIDE@G@A@YCKAIAMAE@CAEAI@A@I@I@EBI@A@A@C@GBEBG@E@EAK@GA@@C@CACAC@KAIAEACCMI@@A@A@@@A@@AA@@@@@@@A@@@A@@@A@A@C@A@ABA@@AC@C@AB@@C@@@A@@@A@AB@@A@@@YBA@@@A@C@@@ABA@CB@@A@@@A@A@@@ABA@A@@@@@A@@B@@@@AB@@@B@@DDAD@BBDAFADEDCB@@A@@@A@A@G@@@C@C@A@@BI@EBIBC@EFCD@D@@DF@H@@ADCBC@IEEAIAEAAAACAE@CCE@@AA@AAA@A@@@A@A@@A@A@AA@@A@@@A@AAA@A@A@A@A@A@@A@@@@@@@@@A@@@AA@@AAAA@@@@@A@@@@@A@AB@@A@ABA@A@A@@@A@A@A@C@@B@@AAA@@B@@AAA@@@@@A@A@A@ABAB@@A@@BA@CBA@ABA@@@ABA@@@@@@B@@@@B@BBB@@@BB@@@@@@@@B@AB@@@@@B@@@BB@@@AB@@@B@B@@@@@@B@@@@@@B@@@B@@@@@@BB@@BBB@@@@@@@@@@@@B@@@@A@B@@@@B@@@@@B@@@@@@@@AB@@@@A@ABABA@@@@B@@@@@B@@@BA@@@@@ABA@A@A@A@AB@@@@@B@B@@AB@@@@@@AB@@A@ABA@A@@@@@A@@@A@A@E@@@A@A@@@@@@AA@@@@@A@@@A@A@A@A@A@A@AAA@@@AAAAA@A@@@A@@@@BA@@@AB@@A@@BA@A@@@AB@@@@A@A@@@A@A@@@A@A@QD]F_FgAYCaGaA]JONSPUL"],"encodeOffsets":[[89288,42568]]}}],"UTF8Encoding":true}