{"type":"FeatureCollection","features":[{"type":"Feature","id":"230708","properties":{"name":"美溪区","cp":[129.133411,47.636102],"childNum":1},"geometry":{"type":"Polygon","coordinates":["@@hcTaLYFQLKdMlK`ONILKIAMEM@KBQDI@MAEC@EFQDOBEJCHCBEAEGEAEDOFEJ@R@PAHEF]@EEEGEOKAE@IJOPOLCL@VFTHF@FABC@E@@A@@@@A@@@C@C@A@@@AA@@@A@A@@AE@EAAAA@@@AAA@@@@@@@@A@@B@@@B@BAB@BABABAB@@A@@B@BA@@@@B@@@B@@AB@B@@@@EAgDIDIPGH@H@FBBADEDO@EK_@EBAL@fCLCDG@KJMFCÀ_JDÃFUAOEIKEK@QBCKCKIEOCw@WB[J_NUNSFW@UCWI_IMCKBSD[D_BW@O@WHOBQB[AaG]KaM_EKGGIIaGcKcIUSUWM[IWAe@eL[BWASG[Qe_omKIOGSCFQ@KAEG@IBaAKCKGIKG[I[OMMIQCQ@QBSBMFOPM`OVMNKHKBOAOkBo@WDUJ[DiA[B[DY@UEq@qC_E@\\ALMPQNUH]FOFEF@JBHJH\\J\\LLJBLCNMHMJILGP@PFF\\HZJVNNNJRFZBTFVPTZ²`|d~Z^VP\\H^B`C\\KPQXcNMNEP@NH^jNXBN@R@TCbAPDLNNxjLNJPLXLTR\\LXF\\Fd@vrPdTj`\\bZpNZ@nJpHlBAXB^HfPTHZDZ@VG\\G\\IRARDLJFRLh"],"encodeOffsets":[[132720,49228]]}}],"UTF8Encoding":true}