{"type":"FeatureCollection","features":[{"type":"Feature","id":"451225","properties":{"name":"罗城仫佬族自治县","cp":[108.902453,24.779327],"childNum":1},"geometry":{"type":"Polygon","coordinates":["@@BBB@BDBAL@D@@ACAAA@AB@DAFADAB@BB@DDDDBBB@DJDLJAH@J@F@BDFFBB@HGJEH@DAHBJDHFH@H@DBBBDCD@F@BA@E@G@CFGF@VABAB@@@B@@@BB@@@BBD@DBD@FBF@FLJFHHFDH@DBDBD@DBBDDFDJALINQRANDNFTLHDJEHICGEKACBGLAN@LBJBJ@HEJGFAJAJBPDNLRPHNDR@NDLDHFFN@LGLAL@LHPJLJJNNNJHFFJ@JGFMNUJGLGLMHQBKBOHSHWFS@QEUCSCUCKGGGGEECIDMCSGGIGISEMGEMEOIOIOIMMQMMIMEKGMMGQ@ODQLUTIZA^E\\D`B`DTJPHND@FCRBJJBNBNBHCLKLODADCDC@GD@HGHAHEFGBC@GAGEGACC@GAE@EACAACCGB]BIBCFADADCCEEGCCCKAK@GBC@@\\BNWEOIQeaC@CFGJKFI@M@IDGF@HAJALAFGFGDIBG@GAIGICOCM@K@KBICKKEKO[CK@EIGOEGCCKEMCKCGEEKEOAIAG@EAIGBCFEFCFAAEGAKAO@GBEFGGAGEM@GDGJGJAHEFMBMBKDGHIFEHAFCDEAGECGGACEMEGGGIAG@KBICICGEQIGEECGGIBOGKEMEGBGDGFCHEHGBICKCKAMAIBKBKBOBQ@GDCBAF@HAHBJCLGHGFCB@@@@ABGBGAKAKGIGGGEICIEICCECECIAICG@EBEFGFGDKFIBIDGBKAGDCH@F@JBHBFCHALAJ@LBJ@F@HAJALAP@HCJEJELGLKLEJMFG@ECCCGIEGEEECECC@CBCDKJEHEFEEAG@GECEACBCDE@GCGGEKAK@CEEGCE@CDADCHAH@J@FADCFGFIJKHGFGBKDGAG@AB@D@FADCDCD@FBFDFFDJDFBDD@HAJCLINGHGFKFQFIHCHAHAJAT@NBD@B@D@BBHDB@F@FAHAF@BDL@F@HAHBDADCBCBE@ABCDADBJABABAD@DDFDDDBFLBFDDDDF@FBPB@B@@@DBD@B@DCBC@CDA@C@CBE@BBFLDDHFFFDHBD@D@D@FCFB@@B@BBF@JABABIFIP@@DHFHJDLBNBLAJCNGJGLCJ@NBNDJ@HADCFCDCH@FBJBLDHFDH@D@H@L@DAJ@HEJCFEHCL@FDDHDLDRHPDHDHFHHDJFHHFFBFBHBHCHGJEJKFGJEFAHBBDBFBDBHBJFB@D@D@TAJAD@BDBD@DBDBFJBDDBBBB@F@"],"encodeOffsets":[[111324,25704]]}}],"UTF8Encoding":true}