{"type":"FeatureCollection","features":[{"type":"Feature","id":"150783","properties":{"name":"扎兰屯市","cp":[122.744401,48.007412],"childNum":1},"geometry":{"type":"Polygon","coordinates":["@@EAEAECICSGKCKCAAUGCAyU]O[I]OSSU[WUgWgQaKcQIqQUEkYSKOKMMAB@BA@ABC@A@ABABABABA@C@@@A@CD@@E@ADA@ABA@@ACBABCB@D@@ABC@@@@B@BA@@BA@C@AB@@A@AB@BGCCBABC@EBE@G@C@E@CAA@A@AH@HA@C@CBA@@@C@MDMDaPM@K@GBCFEBGBGBG@IFKFIHA@SFqFRC@ABCBA@EDE@EDABCFA@C@A@CBE@IBGBA@E@A@CAAAK@AAC@AAA@ABA@AD@@AB@BABEFAD@@@DBB@BA@@BA@A@EAC@E@KBA@ABA@A@G@A@A@G@EAE@ABA@A@EDABC@CBAACC@CCCAAAAIAE@EACAAAACA@AACAA@C@E@EAEAGCEAECE@A@AA@@AA@AAAA@AAIACAEAAAA@C@EAGCAA@@BC@@AACAA@AAACAC@C@CACAACA@AAABA@@AC@AACAACAEAEAAA@A@A@A@A@ACACEACAAAACACCAA@ABE@AAA@@AC@ABAACBCBCDCBABADCDEBAAA@@AA@CAC@AA@KBEHKDGAGAMDIIG@C@SBC@AEGACBCH@DGJCDC@EAI@CBEBCHGDEDEFG@I@MDE@K@A@KCECKCKCEAGEG@EAE@UAKDECW@G@I@[A@KBEEAGAE@@AA@A@AA@A@@AA@@@@@AAA@@@AA@@@@@A@@@A@@@AAAAAA@CA@@@AAA@@@CBA@@@AAA@@A@@@A@@@@CAA@AA@@@A@@A@AAA@A@AAC@@AA@@@A@@@C@C@A@C@EAC@A@AAAA@@@@@AB@B@@@@@@A@@A@CAA@@A@@BA@A@@@AA@A@A@G@A@@@CAAAAA@@@A@A@A@@AAA@C@EBE@A@@@A@@AA@@@C@@@CAA@A@@@@A@@@@B@@A@@A@AA@BC@@BA@AAA@ABC@AB@@AA@@@@A@ABAB@@ABCBC@C@A@AAA@@@A@AAA@A@AA@@@A@@@@A@@A@@@@@@@A@@@@@A@@@@@A@@@@C@A@@@@A@@A@C@A@AAA@@@A@ABA@@@A@@@@A@@AA@@AAA@@A@@AA@@AAA@@@@@ABA@@@CAA@A@A@A@ABA@ABA@A@A@@@AA@@@@@A@@B@@A@@@@ECC@CAKAGAGAC@A@@AAB@@AB@BABA@A@A@A@@AAC@AA@@@@AA@@@A@EAC@@@C@@@A@@@@@@@@B@BA@@@A@@@EBEBABA@C@A@A@A@@BA@@B@@@@ABC@@@A@ABA@AB@@A@CA@@A@A@@B@BA@@@ABA@AAA@AB@@ABAB@BA@@BC@@@ABCBA@@@CA@@A@ABA@A@AB@B@BA@@BCBA@ABA@A@C@A@A@AAA@ABEBA@@BE@ABA@@B@BA@A@A@C@CAMAA@A@@@CA@@A@@@@BA@@BC@CB@BA@AAA@@@AAA@A@C@C@E@A@EBAAA@E@A@C@AB@@@B@BA@@@A@A@C@C@@@@@AB@BA@CAA@@@A@@@AB@@A@C@AB@@@@@B@B@BC@@@A@A@@@A@AB@@AB@@ABA@A@A@CAAAA@@AC@A@A@C@EAA@CBA@AAA@@@A@@@A@@@@@A@@@A@C@ADEAA@@@ACA@A@G@A@@@@AAA@@@@C@ABA@@@A@AAGA@AAA@@@@A@@BA@@@CAA@@@@C@AA@A@@@AC@@AAAAA@A@@@AB@B@@A@ABAAA@@AA@@A@@@@B@@A@@AAECA@A@AA@@@AA@C@A@E@A@@@AA@@BA@@@AA@@@A@A@@@@C@@@AA@A@A@@@AA@AA@AB@@@@A@@A@A@@C@AA@@@AA@@@@@AAA@@@A@@ACACB@AA@@AAA@C@@AAAAAAA@@AAA@AAC@@A@C@AA@@A@AA@AAA@@@@A@@@CCCA@@AA@@@@A@C@@@C@A@@AA@@@AB@BA@A@A@C@A@ABCBAAA@@AB@@@AAA@A@@@@@BB@@@B@@A@@@A@@AA@A@CBC@@@@BA@A@A@@@A@AB@@B@@@@BC@C@@@AB@@@B@@@@B@@@@BAF@@@@A@@@@AA@@B@@AB@AA@A@A@A@A@AB@@B@@@@@@@@B@@@@B@@BA@ABC@@@@@@@BB@@@@C@AB@@@A@@AB@@@@@BBB@@@@ABAB@@BB@@A@AB@B@@C@@@AB@@@@@BBB@@@@ABC@CB@@AB@@A@A@@BA@@@C@A@@B@@B@@B@@C@A@A@@@A@@@@BBBAB@@A@ABC@ABA@ABCBABCAA@ABA@@@@@@BC@A@A@@B@B@BA@@BE@@BAB@@CBA@@D@B@@@@@BA@A@A@A@@@@BAB@@A@C@CBC@A@C@AA@@A@A@@BA@A@@AC@E@@@C@A@A@AAAA@A@AA@A@CBA@A@E@AACAA@A@EAABC@E@CBA@AAA@AB@@BB@@@BA@@@A@AB@@@BA@@BE@AB@@@B@@@B@@@BA@ABC@A@@B@@@B@@@B@@C@@@C@EBAB@AAB@@AA@@ABA@ABA@CA@@ABABABCBCBCBAB@@C@@@@B@B@B@@ABA@C@A@ABADC@@B@BA@@B@@BB@@B@@@BB@B@B@B@@@@@B@@@B@BA@@@@B@@@B@@@B@@A@A@@B@@@@ABAA@BA@@DA@@BC@AB@@@BA@@@ABA@@@@@AB@BA@ABABA@C@A@A@AB@@@@CBA@CBC@ABA@@B@@ABBDABB@@BA@A@@B@@BBA@@@A@@B@@@B@@A@@@A@@B@@@B@@A@A@@BB@@BA@ABA@CBA@A@AB@@A@AAA@A@@@@@A@@B@@A@C@@@A@@B@BA@@@CBCBC@@@E@A@A@@BC@ABA@A@CBC@A@C@A@ABAAEBC@ABA@@@A@@@@@A@A@@@A@@@A@@B@@A@ABC@A@ABCB@BA@A@ABA@CBAAC@A@@@ABC@C@AAABA@A@@B@B@@@@AB@B@@@@@BCF@DBDABABC@C@A@C@C@A@AASGOECBAB@@@B@@BBDDB@B@@BA@@@A@ABA@@BADABAB@D@D@B@DA@@BAB@BBD@D@BAF@@BDBBBBBB@B@B@BCF@BGH@@@B@B@DBBFB@@DD@@@B@B@@BB@@@D@BFDLJLDXFZLPLXLNDT@HDDLEJBLZHRBFJBJGPDBTJ@HKNCFGJOL[JIFOJGFIJMJOFOFQLIHEFYbGLIFOHKHOJGHIHGHEDEFEJHJFHJJJJLHDHEDEFAFKNKB}Ig@MBOHSBkBHNFLFPLJRLJHJFTPNNAFCJCN@JFLNHVLPLPJRFPHRLLFJ@LERKHCPEJBTAJCT@F@NBDH@JDPHJXPTDJCLGJKJENETAVARBPARDLDTCT@FHVRNHLFLHNDRCTAPAXF\\PLHPBRI`J^TLJNHPJNLFT@PFPNRJHRFNHbRNFTLLLLPFPVEVBHCdOT@NAR@VHLD`ENFJLJHPFZJVFLALANAHCTITA\\DPBVHLJFFHJBJAXFFAFADEHAFEBEDGDIBGDIDKFCDGDHHMHgRH`M^HJC\\FJGJEFDDBBBDDB@FAFJBJDLBNFLDNFLDJFJFHDFFHFnPdHXJZN\\LNDXFRDXB^B`CL@RFbLFBZLLBVFHFRLARJPHJBLENBJCPETDLFLBLKLCPRHNPNDfVGrZ^`TXFDCxJZ@nMrUZSLCRGZCdQT@XAXA^CRGTSrOFGTC`^@`FjCTK^CVQMP@Td@L@lMXBHDN@RF`^^NXAfUNBRLxDPHPLJNHLHHNDTDNJNLBJ@NJNJNLHDHMR@LHJJFdLNLPFX@TEXDPBXLATAN@LKPGNET@PITIRCR@H@N@LENDLFLBLANHHVHNHHTARPPFHAL@RDJIJ@J^LDHDL@RCH@HEJKHCJDNNLFDVAN@EDALANJNH\\hENCTJXRPJRBRAREHECQAKJKJCPBT@JCLELKRARLLBPGRKHONMLETCTKNG^ENAPBRATSBQOUBSBSUgCqDMjktCLEbWPWLERCHE@SNa¨^SfoF[^kKcCCH[A_CA@@@@LKDaLIHWhcNE~@KSYC_VUBWJI`OLOdMZUlEdQhKdYjIT@\\LL@TK\\CXGV@FJHBLCB@B@@BD@JAB@B@D@FDDBD@DAHCF@FAF@B@BA@@BADBD@D@DA@@EEIKAACI@EACCGGOCGEGEGCEACGOAA@AAA@C@AAA@AAAAA@CAA@AAAAA@AAAAC@AAAAA@AAAAAAAAA@CAAAAAA@AAAAAAAAA@AAAACAAAAAA@AAA@@AAAAAAAAAAAA@AAAAAACAAAAAAAAAAAAAAAA@ACA@@AAAA@AAAAAAAAAAACAAAAAAAAAAAAACAAAAAAAAAAA@AAAAAAAAAAAAAA@AAAAAAAAAAAAAAAAAAAAAAAAAAC@AAAAAACAAAC@AACAA@CAC@AAC@CAA@C@CAA@CAC@AAC@CAA@CAC@AAC@CAA@C@CAA@CAC@AAC@AAC@CAAAC@CAA@CAC@A@CAC@AAC@C@AAC@CAC@AAC@CAA@CAC@AAC@AACAA@CAA@CACAA@CAAAA@A@AACAC@A@C@C@CAA@CAC@AACAA@@AC@AACAA@CAAAA@CAAACAA@CAAAC@AAAACAAAAAEAEC]KQGQESG_KSEUG]GEAYG]G[ISCA@@@@@AAA@CAA@CAAA@@ECCACA@@@A@@A@AA@@A@AAECAA@@AACACA@@A@AAAAA@AA@@AA@@A@AACAAA@ACAA@AAAAAAA@AAAAAAEA@AA@AAAAAAAAA@AA@AA@CACCCAAACAGEA@AA@@AAAAAAACAA@@A@CCCA@@A@@@@@@@AAAAA@@@A@AAAAAA@AA@AAA@AAC@AAA@@@A@SGKECAEAUIWIUGAASGGCKCEAEAA@GACAC@AA@@@@A@EAEAEACAEAEACACAA@GCA@GCAAC@CACAAAUGEAICC@CASGAAA@A@QKAA@@A@KGAAA@AACEA@@AAAIKACCE@AAAAAAC@AA@@AA@@AA@ACAA@AAAAAEE@@AA@@@AA@AA@A@@AAA@@AAA@@@A@@@@@@AA@@@@@@@AAA@AAA@AAA@A@A@AAA@A@@@A@A@A@AAA@C@A@A@A@A@A@A@AA@@A@AA@@AACAA@@@@AA@@@AA@@AAAAA@AAA@AA@AA@AACAAAA@@A@@A@@@@@A@@@@@@AAAA@@@@AA@A@@@@@A@A@@AA@A@A@@@A@@@A@@AA@A@A@@@A@AAA@@@@@A@A@AAA@A@AAA@A@C@A@@@A@A@@@@@@@@@A@@@@@AA@@A@@@@@@AA@A@AA@@A@@@A@@@A@@AA@@@AAA@@AA@AAA@@AA@@@@@A@@A@@A@@@@A@@AA@CA@AA@AAC@@AA@@@@@@@AAC@AAA@AAA@@AC@AAA@CAAACAAACAA@CAAAA@ECA@@@@@@@AAA@@@AAAAA@@@AAA@AA@@CAAAA@CA@@AAAAA@CAAA@@@@EA@@CA@AA@CCC@ACA@AA@@A@@AA@ECCACAEC@@CC@@AAA@AAEC@@"],"encodeOffsets":[[125357,48487]]}}],"UTF8Encoding":true}