{"type":"FeatureCollection","features":[{"type":"Feature","id":"510521","properties":{"name":"泸县","cp":[105.376335,29.151288],"childNum":6},"geometry":{"type":"MultiPolygon","coordinates":[["@@BB@@B@@@B@BC@@@@A@A@@A@@@ABABABAFCNGB@D@BBB@@B@@BDB@@@@@@@@@A@DBB@@@DDB@BBB@D@BB@B@B@BABEBCDABABBBDBD@L@DBBB@B@B@DGDCB@D@@@DFBB@B@BAB@@AB@BC@AB@@@BBBDB@B@@@BB@B@AB@DB@@B@B@B@@@B@B@@@B@@BB@B@@A@ABC@@DBBDDDDD@@@@@@FBLDF@F@D@BADAD@B@BBBB@BBD@F@DBBF@FCDCFCBABC@A@A@CAC@A@@@A@AB@B@D@D@B@B@@A@A@AAAAAC@C@A@AAA@@A@ABA@A@@@A@C@AB@BA@@@A@AA@AAAACAEAA@AA@AB@@@BAD@F@D@DAFCDAB@@ABA@@@A@@@A@@@@A@BAD@J@FAF@FBZLDBB@D@DADA@ABAAAGK@C@CFGHCDAF@DBLJD@FBB@FDD@FBF@DAF@BAB@B@DBBB@@AB@@BDBB@BB@DCHAFAD@B@B@B@FCBADABAB@D@D@HBJDHDB@B@BA@@B@LBDADA@EAIAM@ED@FBBDDJDFBHBDRLFFHAFADCHE@EISDEFEHCHAH@@AD@H@JBHJBHADEFEFAD@F@BDD@AB@FADAB@H@LB@B@@AB@@BD@@ABBFBDFHHFLJJDHBLCJCDEACQAOAIACGAIBKBIJUHQLUAMAIAC@ABCB@BAB@B@B@BA@@EOCGCEAC@A@ADC@C@E@G@K@AA@AEA@@C@ABCBAFAF@D@D@@BDAB@BABABCBEFIDGBABA@@@AA@@@@@@ABA@@@@@A@A@@AC@A@@@AB@B@@@BA@@CK@C@C@CBABADAH@LLDBFAFADE@GICOEICEIAKCG@C@E@ABEFEHEFEBCBEBGBEBEFCFAD@FAB@BE@E@@@@@@@@@@A@@@@A@@@@@AA@@@@@@@@@@@@@A@@A@@@@@A@@@@@@@@@AAA@A@A@@AA@@@AA@@@@A@@AA@A@@@@@@B@@@@@@AB@@@@@A@@A@@@@A@@@@@@@AA@@@@AA@A@@A@@@@@A@@@@A@@A@@@A@@A@@@@@@@@@@@@@A@@@@B@@@@@@@@@BA@@@@@A@@@@@@@@@@A@A@@@@@A@@AAA@@@@@A@@@A@@A@@@@@@@@@@A@@B@@@@@@@@BB@@@@@@@@@@@@AB@@@@@@@@@B@@@@@B@@@@@@@B@@@@A@@@@@@A@@A@@@@@@@@@@@@@@@@B@@@@@@A@@@@AA@@A@@@@@@@@@@AB@@@@@@@B@@@B@B@@@B@@@@@@@@A@@@@@A@@@@@@AA@A@@@@@@@@B@@@B@@@@@B@@A@@@@@A@@@@BA@@BA@@@A@A@@@@B@@@BA@@@AB@B@@AB@BAB@@@BA@@A@@A@A@@@@@@B@@@@A@@A@@@@AA@@@A@A@@@A@@@@A@@AA@A@@AA@@A@@@@AA@@A@A@AA@AA@@A@@A@@@@@A@@CACA@AAA@A@ABCA@@A@@@A@@@@@AAE@AA@A@A@@AAC@A@@AA@@@AA@@C@ABAAACA@AAAAAAA@@@A@@@@BA@A@@@A@ACCCAAA@C@A@A@A@CA@AACC@A@@@A@A@@@A@@@AB@BA@@AA@@AAA@G@A@AA@@A@@ABA@@AA@AEC@@AA@ABC@A@@BA@@@AAAA@C@C@ABIHAB@@AB@@A@@A@AAA@A@@DG@AAA@@AC@A@AA@@ABABC@A@ACAACAAAAAGA@@AA@AB@D@BA@@@A@CAA@ACA@@@A@AB@@AD@@AB@@A@CAGEAAC@@@AB@B@B@BEBC@C@@BC@CBA@E@A@A@A@A@@@AAA@EAEFKH_FSLMPCPA@EHGFGBEDGBCBCBC@GAKAEACA@@QIMOEDCBADAF@H@H@NBFLFDH@FBDFBFDBB@BAFELABA@@B@@B@B@@B@@@B@@@BABA@A@A@@@ABA@CB@@AB@@AAA@A@@@A@@@A@@@A@@B@B@@@BCB@BA@@@A@ADEBCBCDABABA@A@AACAE@C@CBAFBP@B@@@@BBB@B@BABAB@BB@BBDDDDDBD@DABC@CCCAECC@ADCBCL@@EBCBC@ADABBBBD@DC@C@GEGG@E@GCCCCAEGGKGG@G@G@CD@D@BDH@B@B@B@@A@A@AB@BAHBB@BBB@B@DA@ABAD@D@D@BCBABCBCTABEBEGAECCGAGBG@CCIGEAEAC@C@ED@@@@BBA@@@ABABA@@@A@@@AA@@A@@@@B@@@B@@@@A@@B@@A@@@A@A@A@@A@@A@@B@@@@@B@@A@@B@@CB@@@@AA@@EDEDI@EBABEFC@A@AA@CBA@C@A@@@A@@@A@@A@@A@@@@@@@A@A@A@@@A@@@@@@@AB@D@@@B@@@@@AA@@@@A@@A@@@@@@B@B@@@B@@@B@@@@A@@@@@@@AA@@@A@A@@AA@AAAA@@A@@@@@@@@B@@@@@B@@A@A@A@@@A@@@AA@@AA@@@@@@BA@@@@@@BA@@A@@@A@@AABA@A@@AA@@@@A@@@@BA@@@@BA@@@@@@AAA@A@@AA@@A@AAA@@@@@@@AABA@@@A@@@A@@@@@C@CAA@A@ABCBCBC@AAE@CA@@@A@CDGBC@@DEBABAB@D@B@@@BA@@EE@@CECECEAEAAEI@A@AAC@CBA@A@A@A@@@@@@AACCAC@C@A@CAEEGAGEI@I@G@CBCDADC@C@CCAA@@C@A@A@@D@@ABABCBABADCCCAA@GAG@CACCAC@G@A@O@IBC@CBCDCFCDE@EAMKCAA@C@ABADCD@F@FBDBBH@HBDBDF@D@F@BA@@DADABABABABEFAD@BABAB@D@DBD@B@BABABAB@@CBA@CAGACAA@A@A@@@CACCAEACDIBAFCDCBA@CAA@ACCAA@@@@A@EBC@ABAB@@ABAB@BA@A@C@@@C@EBCBEDADAD@D@DDFPJ@@BBBDB@@B@@B@D@B@@BDBHDDBDDB@@BBBBD@BBB@B@BAD@BAB@B@@BDBD@B@@@D@BE@ABA@@DBDFJ@FAD@BA@@@A@ACAAC@CBC@G@I@CD@DBBFDBB@BCBC@GBE@GDGBAACCAAACCAABADEBGA@@@ACC@A@AACAAA@ABA@ABA@A@C@C@EBABADADADEBE@E@AB@DAH@B@BAB@DBBBDDBBB@D@DADAD@F@D@DBBBBB@BBBBDFBFHDHBF@DD@@BDBBBDBDBDBDBBBBDBDDDDDDFDDBDDDFDHDFDDBDBBDBFDBDDFBB@BABAD@BABADAHAD@DBBDBBDDDDDBBFDDDDBDFDDDBBB@BFDDB@D@BAD@@@@A@A@@@A@@@A@@B@B@BBBD@@B@BABABA@QDCB@DAD@DBBB@D@F@@@D@BBBDBB@FBBD@D@B@FAF@F@D@DDBDBD@F@F@BAFBJ@DAD@DBFBBBDHFDDBBDFBDDDBFBDBDBDHL@DBDBDHJDFBBFDDDFDBDXTBBD@DAD@D@BBDBBBF@FBDDJJ"],["@@@@@@@@@@@@@@@@@@@@@@@@@@@@@@A@@A@B@@@@@@@@@BB@@@@@@@@@@A@@@@@@@@@@@@"],["@@@@A@@@@@@@@@@B@@@@@@@@A@@@@@@@@@@@@@@@@@@@@@@@@@@@@@@@@@@@@@@@@@@@@B@@@@@@B@@@@@@@@A@@@@@@@@@@@@@@B@@A@@@@@@@@@@@@"],["@@@@@@@@@@@@@@@B@@@@@@@@@@@@@@@@@@@@@@@@B@@@@@@@@@@@@@@@@AA@@@@@@@@@@@"],["@@@@@@@@@@@B@@@@@@@@@@A@@@@@@@@@B@@@@@@@@@@@@@@@@@@@@@BB@@@@@@@@@B@@@@@@B@@@@@@@@@@A@@@@A@@@@@@AA@@@@A@@@@@@"],["@@@@@@@@@@@@@@@@@@@@@@@@@@@@AC@B@B@BB@D@CA"]],"encodeOffsets":[[[107893,29995]],[[107894,29997]],[[107918,29991]],[[107898,29990]],[[107916,29988]],[[107914,29987]]]}}],"UTF8Encoding":true}