{"type":"FeatureCollection","features":[{"type":"Feature","id":"130402","properties":{"name":"邯山区","cp":[114.484989,36.603196],"childNum":2},"geometry":{"type":"MultiPolygon","coordinates":[["@@ACD@BACCCCECGGABCAABA@AA@AACCBCDBDBBFB@DG@ID@DA@CB@DCBCAA@@F@B@BC@@ACCABCB@COAACK@GA@DB@@AHBBBDB@@DB@H@@FHDB@FCBB@@DBBHDNDNJD@@@LAHBBHD@@@F@RA@C@@C@@@BA@C@CAA@I@@BAAKH@@CD@@CCCACCA@@@C@@A@"],["@@AC@@CAABC@A@E@@BA@@Y[@@@AKG@@I@ME@@BE@@@@B@D@DABAAA@IFEDCBAAAA@CGBBFGBSBCDBFT@BRF@J@FRHTBB@B@L\\@lETA@@F@@@@@H@F@RAD@@@@@@AAC@AE@@@@@MB[D@EA@@AA@BABAF@@@C@EGDCD@BAD@@@H@H@F@FAFA@EG@@GCDK@@BIBA@EBA@@@"]],"encodeOffsets":[[[117194,37347]],[[117265,37460]]]}}],"UTF8Encoding":true}