{"type":"FeatureCollection","features":[{"type":"Feature","id":"511622","properties":{"name":"武胜县","cp":[106.292473,30.344291],"childNum":2},"geometry":{"type":"MultiPolygon","coordinates":[["@@LDNFLDH@F@F@HCHADABCFCBCBC@EBAAE@ACC@AAACAECCAC@CAC@GAGCGCAAAA@AAABC@ABCFCBEFCFKDC@A@C@IBEAC@@@C@A@CBC@ABAB@B@BBD@B@D@B@FABABAFCFEJEDCHEDE@ABCBABAB@BADBB@BBB@DB@BB@D@F@F@FAJAFAB@F@DBJDDBFDH@DBBFFBDBF@B@F@FABAB@@AB@@ABABCBADABCDEBC@@B@B@BBBB@B@B@FBDBBDBDBF@B@DAD@DDBBJJTJHFDBFBDBB@B@B@B@D@D@BBBBDBFBF@F@HADCD@D@F@HBFBF@J@JADAD@D@FAF@D@LAD@DCDADADAD@DA@A@ACCCC@A@AF@B@D@F@F@BA@A@A@A@G@GBCBEDCBCDEFCFCDAB@FADBB@B@BADA@AF@DADCB@BC@C@AAA@AAA@AAC@ABA@A@C@A@A@ADC@A@EAC@EBA@CDCBADCDCBC@AA@AA@@A@@ABA@A@AB@@CB@@AAAAA@A@C@C@CB@@AB@@A@@@AAA@AAA@AACCAE@@AAAAAAA@ACAAAACAACCA@A@CAA@A@@@AAAA@A@A@A@ABABABCBABABCDCDCBABABADE@@BA@@@A@A@@@@BAB@AAAAAAAC@@B@@ABAB@BABAB@@AB@@ABABA@C@CAAAAA@ABABCBABADC@C@AACA@AAABA@ADCBADEBCBC@CAAE@CBC@GBCAC@@@@@@@@BA@@@A@A@AA@AA@AA@@@@AA@@@@A@@@A@ABA@A@@@A@@@BA@ABA@@B@BAB@@ABABA@@D@BBB@B@B@@ABAAA@C@A@@DCB@B@F@B@B@BCA@AI@CA@E@E@I@@@CA@ABAACAA@CAA@@@AC@C@EACAA@@@ABA@@BADADABABABA@ABABABABCBA@C@C@AAA@BC@CD@BABAFG@A@@AAC@ABAB@B@B@BA@@@A@ACA@A@CBCBA@C@ABA@AAAACAC@AA@ABA@@@A@@@@A@A@CAA@@@ABA@@@@BA@AA@@CBA@@@AB@@CBA@AB@ACCAAAA@C@AA@@@@AC@CB@@ABA@CA@A@A@A@ABA@ACE@A@A@AA@A@A@CBA@A@CDA@ABA@C@CAA@ABAB@BADC@@@@BA@ABA@@@AB@@AB@@A@A@A@@BCACBC@@AA@BCBAAA@@@ABAB@BA@@BADE@A@@CAOGGAAA@EBGHM@@@AAAC@@A@@@AA@A@@B@@A@@BA@@AA@C@C@@A@A@G@@AACAC@@@A@@B@D@F@HBB@D@DCBCBA@CAA@A@ABB@@DA@ABC@A@C@C@@A@@@CDA@AGC@@@B@@@@A@@B@@@@@AA@@@@AA@@@@@@@@@@A@@@@BABA@@@@B@@A@@@@@M@@A@CAABAB@@@@A@@B@@A@A@@@AA@@AA@@A@@B@@C@CA@C@@BABCBABA@A@AA@CAACAABABC@A@ACCCAAB@@@JAD@B@@A@C@C@C@ABAB@B@B@BBB@@BBB@B@DBBB@@@B@@ABB@@@B@@@@D@BBBAB@BABAFCFCD@@CDABA@AACACCCAAAGECAA@EAEBEBCBAD@D@DCDA@E@AAADC@@@ABAB@@B@@BDDBB@@BB@BBDBBBDB@@B@@@B@@AB@@@@@B@@DBABA@A@CAEACBE@CBA@E@C@@@A@@BBB@@BD@BB@@@@B@B@@@@A@@@A@A@@@A@@@@B@@@B@D@B@B@B@@@DA@I@CBAB@DDBFDFDBBBB@D@BA@@@@B@@@@@BBB@@B@@B@B@BAB@B@@@B@@B@@@@B@@@@@BA@@@A@@AAAA@@@@@A@A@@@@B@B@@@DB@@BB@BBB@BB@@@@@B@@C@AB@@A@A@A@@B@@@@DDB@@B@@@@@B@@A@A@@@@@A@@@@@A@@@A@A@@@@B@@A@BB@@@B@@D@@@B@@@@@BB@B@@@B@BAB@BAB@@@@@@BBBB@@@@@@@BA@A@@@A@@AA@@@AAA@@@AA@@@@@B@@@@@B@@A@@@@B@@@@@BB@@BBD@BBDBB@@@B@@@@A@@@AA@A@@A@@@A@@@AD@@A@A@@@@@AA@AA@@A@@A@@B@@@@BBBB@@@@@BAB@@@@A@C@@@A@@B@@B@@@DB@@@@@@@B@@A@EDAB@@A@A@@AA@@@@ACC@@AA@@A@@@@@AB@@BB@B@@@BAB@@A@AB@@A@@@AA@@AA@A@@A@@B@@A@AB@@A@@@A@@@AB@@AB@@@@@@A@@A@@@A@A@@@@@A@@A@A@A@@BA@@@@@@@BBBBB@@@@@@BA@@B@@A@BB@B@@@@AB@@@B@B@B@BA@@@@@A@@@A@A@@@A@@@A@@@CB@@A@@@A@@AB@@AB@@A@@@A@@@AAA@A@@B@BABAB@BCBA@ABAB@BA@AB@@CAEACA@@@A@A@A@A@A@@@AB@@@BDB@B@@A@C@A@A@@B@@@BBD@B@B@BABA@@B@AA@@@@@A@@BA@A@@@A@@@@BA@@B@@A@A@A@@@A@@A@@@@@A@@B@BA@@@@@AA@@BA@A@A@A@@@AA@@@A@@B@@AA@A@@A@@A@@B@@@@@BA@@B@BAB@@@@@@@@@@@@@@@@A@@A@@@@@@@@@@@@@@@@AB@@@@@B@@A@@@ABA@@@@@@B@@@B@@B@@@B@@@@A@@@@B@@@B@@@@BB@@B@@AB@@A@@@A@A@A@@@@@AB@@@B@@@B@@@@A@@A@@A@@@CB@B@AA@@A@@A@@@@@AB@@A@A@@@AA@BA@@@AB@B@@B@@@B@B@@@@D@DBDBD@B@B@BCH@B@B@D@BABA@@@EAG@AAA@@AAE@AAC@AA@@@@A@@@@A@@@AAAA@@AB@@@@@@@BAB@@@@A@@@@B@@A@@@A@@@@B@@BB@@@@@BB@@@@@BB@@@@@@AB@@@@A@@@@@AA@@AA@B@@A@@@A@A@@@@@A@@A@@@@BA@@@AA@@@@@A@A@A@@B@@@@@@@@@BB@@@@B@@@@@B@@A@@BA@@B@@A@@B@@@@AA@@@B@@@@AB@@@@@BA@@A@@ABCDCDCBA@CAAAA@AD@D@B@DABAB@@A@A@EBABAB@D@BAF@DA@@B@B@DABA@C@C@AAAA@@CAC@C@C@CBEBCBEBA@@@ABA@A@@@A@@@A@@B@D@BADBB@BBB@BABA@E@E@CB@B@@@BDBFBFBBB@B@BABA@@@IAGAEAA@AB@BABAB@D@@B@DBB@D@D@BB@BABABAD@BBB@D@DABC@AACACDAB@@AB@B@@AD@@@@@F@B@B@@@D@DABEBCBCBC@CC@ABC@A@AA@C@C@ADCFCDADCBCBCDCDAFAF@FBDDFBDDBD@FAFAF@F@DBDDBDBFBHBHAFADABAD@@BBDBBDDDBDBDBBBBB@D@D@FADAB@DAB@B@B@DDBBBBBB@BD@@@D@BABABA@A@A@A@AB@B@B@DBB@D@B@D@BADABAB@BAB@A@@B@@B@BB@@BBBB@@@B@@@B@@AB@B@@@@BBB@AB@B@B@@BB@@BBB@@@B@@@@@@@@@@BA@@B@@AD@@BD@@@BA@@@CB@@AB@B@@BB@@B@BB@@@B@@@@AB@@BBB@B@@@B@@@@B@BAB@@@@BB@@@BB@@@@BB@B@BB@BB@B@@@B@BABABADA@@@@@AB@@AA@@AAAA@A@@@ABA@@@AA@@@A@A@AB@B@B@BBBBB@BB@@B@DAB@@@B@B@@@B@B@@@@A@A@A@CAA@@AA@A@@@ABAB@D@D@D@B@BAB@B@@@@BB@@@B@@A@AAA@A@A@ABABA@@BAD@D@B@B@@BBBA@@B@@@B@@@@B@B@BAB@BB@@BBBB@@B@@@B@B@BA@ABABAB@BB@@BDBD@B@FBBBBDBB@BAD@DADABAB@D@B@BB@@B@DBDBBBBB@DBDBD@D@DBD@B@FAD@DA@BF@DB@@BB@BB@@DBDB"],["@@@@FA@@DADABE@AAAAA@A@A@A@C@A@@@AA@CAAA@@BCB@DCBA@@@CA@CAEBCB@F@B@B@@@@BD@@@B@BCBABA@@N@@BB@@@@@@@B@@@B@@@@@@@BA@@@@@HD"]],"encodeOffsets":[[[108671,31267]],[[108815,30935]]]}}],"UTF8Encoding":true}