{"type":"FeatureCollection","features":[{"type":"Feature","id":"411626","properties":{"name":"淮阳县","cp":[114.870166,33.732547],"childNum":1},"geometry":{"type":"Polygon","coordinates":["@@AC@@FC@A@E@@@@AU@A@@BAJ@H@HCHCBABA@CAG@OBEBGDEBA@C@GBIDO@Q@@@@BI@EDEJG@K@EBGBK@EACAAAACAGECEACAEBEA@@AE@CACAAIAE@E@IACACECCCUGEAAAAC@ABE@I@S@CAAKIOKGEEECC@C@U@E@C@AACGCGECCCEACAC@CBEBC@ABEAABABEDE@@@EAE@A@A@@@@B@BAB@@C@A@ADG@ABADADCFCFADADCFAD@DAB@D@@AB@DCDEHGFEHEJIAK@C@@@@I]GOCM@EBCBCBABE@E@GDY@I@M@CBGFGBC@C@AAE@CBIBADCFEBCDI@C@AA@AAC@A@C@AACAGGKIAA@C@CDGBE@A@CCAAACAC@C@A@AAECC@CACAA@KB@AAA@C@CAQBCBA@CAA@CAEACAAAACAEEACAAGFCB@@@@CBEBEBA@CAMCEAC@A@A@CBADCBEDGHINCHCFCJCJEFCDGDEBC@G@OCSECAK@I@G@CBCBCDEJGLAHADBF@DBBFBJBBBDF@D@BADEFMLULIDA@C@A@A@IFCDCBAD@B@BDH@D@F@D@BAB@BIJEFMN[\\IJCBE@MBEBCBABELABCBAB@HDH@D@FF@RI@@FNJBB@BHHN@BDNB@NA@@JHDADL@@KNB@ABMFKEIJ@JIB@@K`ENDDDB@@DJGNA@MDBL@BIBA@ELG@@AOJI@KEA@DQKGAAAMO@EOF@@CBC@AAACC@A@A@CBA@A@@CACCEAM@AAA@@A@A@A@KAAEEA@AAC@C@C@@AA@B@@@@A@@C@A@CA@ABGD@B@BA@ABC@C@@BA@@AA@@AA@ABA@A@@@A@ABC@A@@@A@@@@A@KFCGEFCFCDCNAFGJGJITEN@BABC@@@@BBBFDF@F@DBBD@D@BA@GAC@A@@BABA@E@G@ABGBIFGLEFGDGBCDGHKPALAL@HADADCDKDBN@LAf@R@DDBH@J@F@H@FBFBPHDBD@B@BE@AF@\\DRDBBBB@HAHBL@H@H@D@D@D@BABABBB@B@J@BDDBBDDDB@D@J@FAFEFEFCF@D@HB@FDBBDD@BADABIJAD@H@J@FCFINCH@FBFDFNXDJDLHLDJ@@B@BDFEDED@DAD@BABADAJAbCV@@@@@P@FAPEF@F@HBB@J@hDXBHDLDJDJBJ@PAHARED@LBFBDAL@FBRDT@H@JCH@R@X@J@HCLGLARCFADAD@D@DDBDBBDBRDBBLVHDH@D@HARG@@@@^M"],"encodeOffsets":[[117816,34724]]}}],"UTF8Encoding":true}