{"type":"FeatureCollection","features":[{"type":"Feature","id":"361022","properties":{"name":"黎川县","cp":[116.91457,27.292561],"childNum":1},"geometry":{"type":"Polygon","coordinates":["@@D@DB@@DBB@B@D@BABEBCBADBDBDDDDBFBBBDFDDBDBBDBDBD@BBBD@DBDADCDCDEBC@A@A@CAAB@BA@A@A@AB@@ABAFADAD@DEBABE@I@GAG@E@I@EBE@@BADABCBC@EBCBA@@B@B@BCBACAA@@@@ACCAACC@AAC@A@A@EDCDADCBA@CAAACAC@CDC@CAE@CDCDCJEB@D@DBB@BA@@@A@ABE@K@E@C@A@A@@@AB@BA@A@@BABCBABABAAEAEAGACAC@EACCCACCCEAECEAAAKCAC@A@E@E@C@ACAC@AACA@ABEDEBCBC@CAC@AACACBCBE@E@EACAE@EACBEDEDEDAFE@@@@B@B@BBDBDADAJCDAFAB@D@D@B@B@D@B@@@B@B@@@BA@ABC@EACAECAACAG@AB@LADAFB@@D@@@F@H@BABEDEDCHAH@DCAEAEAEACAA@CBA@@BAAA@@AAA@@C@A@EA@ACAAE@ABCACACC@E@G@CEECCAA@CBCBAACCACCEAACACACCACCCCEACAACACAAAAA@A@CA@@AEAEACAACAEACAEAC@CB@BADA@C@CCCCEKEGAEACAEAAACCAAACACACACAA@CACACCEGGGACACAE@CCACCEACAAAACAA@A@CAA@CAC@E@GDIBIFGBC@IBIBEBC@A@A@ACAEACAA@A@IEMIYEOAOGGA[OKGMEMGQQQUEICMIQGEQZQDQBKASA[KIKOIMISCWFOHQBIBQESEOAQCQEQKIUEKOFGFWHSAOBKAFLBfBPHbBJ@T@\\@LH@JAFDBRAVBJ@LHTIPIFILCR@VMJEF@JDLFLIN@NDTAVDNLHXFT@HEZGDBAJGJMp@RELQZIPHJDPADENKLBHP^FJFNCJAHIRCP@LFNHNJJNLPF@@FABAHEDCF@BDLD@FB@@B@B@BA@HDDDF@DBBBBF@D@F@D@F@HAD@@FABG@@LM@AB@B@D@@@B@DH@@B@BBBABBB@BB@@FAD@FAD@HAD@LGBCF@D@DCBC@AHEHCVKLGPILCFCDCAEAKHMFMJGVCNDLFLLNNLJDFBPANIRELCJE\\CTDPFNLNPNPFJHNFJFPLHJbNHRHNLBVDJHPN@F@@FAD@@B@DADCFEF@B@BHBJDBD"],"encodeOffsets":[[119851,28209]]}}],"UTF8Encoding":true}