{"type":"FeatureCollection","features":[{"type":"Feature","id":"440607","properties":{"name":"三水区","cp":[112.899414,23.16504],"childNum":1},"geometry":{"type":"Polygon","coordinates":["@@@G@GDCDCBABCDC@@BABA@@@A@A@@@CEAAACACAGAE@IBKBBE@C@@@@@A@IDI@@@@@@UAGFCBABABA@@BA@@BAB@@A@A@A@A@A@A@CAE@C@EAIAC@C@GBCBA@A@C@AB@DABAD@B@D@@ANEFGF@GBIIEA@@@@@IAMAMCEIJCHIAM@A@CEGEEAACACCAACGEGAACK@IAEHK@CEAC@AA@@@@AA@@@@@@@@@@@@AC@@@@GEGA@ACCAAAACAAAC@A@A@@FIBECCCEEBG@CFIDEDEBCBA@@FEDCFCDCBEC@CDCDAD@@@@A@A@@@@@A@C@A@C@EB@@E@C@C@C@C@C@CBAAA@A@A@@ACA@AA@DK@GEAAEIAKD@CDGHIDGFMDK@@@@@@AMEQDKB@@CAA@CAA@AA@@AAAHMDIHGBMAEAC@KFGJ@HE@A@ADEN@@@@@F@BABAAG@@BCB@@CA@@AAABAB@B@@AC@AADABABC@AEB@A@@DC@ACA@BE@A@AAA@@@D@B@@AD@@@AAC@@@AAB@BACABC@A@AA@CAAAC@CAA@@A@AB@@DB@@CAAAAADIE@FICUEANCLIRMRGJMLCDABABABA@AD@BAB@DADADAD@DCLEPKZIVAVBTGLEJGFEJGTCR@\\A^ALELQPKJGHAF@HBLAHAFCH@D@DBD@B@@@FA@@@A@C@CBC@AB@BBDBD@F@F@BDBD@BBD@BD@BA@A@@@AAAB@@@HABDBBBF@F@DBD@BAFA@AECCE@AFGBCAEBCDABBB@FBDBBBB@AB@BBD@BAD@B@D@BBDBB@BADFFDA@CBCB@BC@CAAFGBE@AAACAAC@EAE@AT@FZ@DBDNADAD@B@@@@@J@FDBBHHBBFBDHBDDA@D@DCC@DA@AF@@FB@DG@AC@BCDC@EDGDGBGGEE@B@B@BBDBBBDBD@@@@@@DBBDDBBDBBJDJJHD@LFLJHJRJHD@DDBFBFBLDVHPLZDVOFWAG`W\\SRODaF@@ECEC@@CA@CBGAIFE@ABAACECC@GBM@KFA@AB@B@D@D@B@F@H@H@F@B@BFHAJ@@DDJF@B@B@BBB@@@B@F@F@F@F@B@B@BBB@BB@BBBB@@BBB@BB@@BB@B@B@B@B@B@D@B@BABFLDHDJB@BBBFF@BBF@HDJBHDBDDD@H@B@BBBBBDJFFHC@BB@AF@J@H@JBFBJDJ@RBFABIHGFC@GBEB@JAF@FEFAHAHDPD@F@HCFBHDD@FAFBHDFDB@BB@@B@DBDA@CJABBB@BGBABBDCFCVOHE@DCDLJ@B@BAB@B@@FD@@FC@ALEBABCBA@ADA@AB@@@@AB@@A@@@AAA@C@AAAACAA@Ce]IS@GLE@@@ABA@C@C@ABCBCBCBCDCBCBC@ADCBAB@B@BADDDBBBF@DCDABAD@@BD@BADA@EBCACACAAACDABABBBFB@BABA@CAACACABEBAF@D@FAHCFEBADAHCBCDEFAF@FDFFBDBBA@@B@@AF@BDDDBF@D@@@@@@CBCAI@@ACA@@ECCCCA@A@CBCACA@GAEAEAC@EBEBAF@BDDDDDDDD@D@DDDFBFB@FBD@DDBABA@E@CKC@AA@@A@@@A@ABAB@@AB@@AB@@CBA@CBA@A@ABCBA@@BA@@D@BC@@@ADGD@BA@ABAB@BAAAA@A@A@A@@@A@@AAA@@@AA@@AA@@@AB@@A@@@@AAA@@@AA@CAA@@A@A@@@ABABCBA@A@@@A@@@@A@C@A@@AACA@@@BA@@B@B@@@@A@@@A@@@AC@CAAA@CBADAB@CCCA@@AADCB@B@@AB@@A@@BA@AB@@A@A@C@C@C@A@A@@@A@@BABAB@B@D@B@D@BBB@BAB@B@B@BAB@BAB@BA@@B@BB@@BBB@B@@@BAB@@A@E@CBCBA@CDAB@BFDBFBFFBFB@DFB@BBBBB@D@B@D@BABABABA@A@AIMECAEECCCCCACCG@@@@AEBAFEDAB@@D@@F@DADABC@CEAAC@EAGAC@E@E@AB@B@B@BCBEBA@AA@AADCHGFCF@BADCBC@EAIBAB@BC@CCAA@AGEGEE@CF@"],"encodeOffsets":[[115761,23809]]}}],"UTF8Encoding":true}