{"type":"FeatureCollection","features":[{"type":"Feature","id":"420304","properties":{"name":"郧阳区","cp":[110.812099,32.838267],"childNum":2},"geometry":{"type":"MultiPolygon","coordinates":[["@@HBH@J@D@\\BB@LAF@JAD@JAD@H@H@LAF@ZAF@D@L@DA^EJG@@@@^YBAH@dNNBF@DBRFLd^NDBF@DBH@BBTJBBnjBBZJBBB@N@B@B@D@F@DG@EAMCEGIAEAGCCEC@EDAHAJBH@LDB@@B@BABAB@@BB@BD@B@D@B@B@B@B@DDBDBD@D@F@F@D@BAB@BAB@D@DDF@FBFBFDBHEJGDADCBCBABA@@ACA@A@CBCB@@A@AA@@@A@@B@FE@ABA@@DCB@B@DDB@BBBB@FDFBFBLBFDBH@BCDEBEJGBEBCDCD@FBDBF@DMAIAEBGBA@CCCACDGDCHGDEHCRCL@JBLDJHLHXJHBJDBBDD@FADEDCBAD@DDJBF@D@FAH@DAHAD@DHBLBDBBFBHD@@KAC@E@CF@HDNLDBDAD@DCACCEAE@EDAF@DBDD@FF@DAFBBBAHCDEDAB@DBDFJ@DCDCDEDAFGHBDDB@FBDDBFADCDCFCD@J@HAB@JDF@FAAA@GBAHDDDDBCHCHCBBDBDBFAFCDAD@DBDBD@DCFCFFBFAFADDBF@H@DCDEDCDAH@HBHDFFDHBNBDD@DIFGFCBEDEDE@AAEB@FE@AAGBAB@FFBF@D@@D@DBFFBD@DBEFABCDABA@CBABABCDCBC@EBA@EBA@ABA@AB@BADABC@AB@@ABADADAD@BB@@BB@D@BABABAD@B@@BBB@D@B@B@D@B@B@F@B@BBF@RFLJFFDJLHFTFNHPRJNPPHNLNFJDFVWROPMRARF@JCL@NHRLRRLRNPFZFR@PARAHABBB@DBBBBBBDBB@@BBFDDD@@D@@ABE@A@ABCBAB@@AF@B@BBDDBBDF@B@BCD@DABAB@DADADAD@B@BABBDBD@B@BBF@DBD@DDDBBBBDDBBBB@DDBB@DBD@FBB@BAD@LFD@D@B@B@BAB@B@DBBBBB@DBB@BB@BB@@BBB@`CPEPGLAVDTPNPXZPPNPHFLFP@BBDAH@D@DA@@V[BCBADAB@FADABA@@B@B@D@BABABABC@ABA@CDCBCBABAD@B@BAB@B@FEDC@CDEBAREHEU]@@ABC@A@AAA@@A@@@A@@AA@@@AA@AAA@AA@CA@AAAACAA@CCAAAAB@@A@@F@D@BBD@B@@BBB@@B@D@B@@@B@BD@@@@B@B@@B@@XOOSFGJBTTNNVLPDP@LCHEFILOJELAHCBEBBBBDBJD@A@A@AAAAAAA@@@@@A@A@@@@BAB@@ABA@A@MBARMVMNEB@D@B@BADCB@B@B@HCFCHCBECEAC@AACBC@CBCNKLMFOAMUIGAQAMGIEMIEG@MJEPDTHNDL@vA^CRAJEFEBIEKDMNGXSJOJUFQDMKQKGEAKEELALGFO@IGK_A]EUWQUGcCUGMIKKWSSIQOGYCWCQOOQOKQKWCSBMBMFKPSACIC@AAA@AE@G@A@A@ICC@I@G@C@ABA@ABCBA@EBEDCBABCB@@CBC@C@A@G@GAA@CAA@AAC@C@C@CBA@CACACCAAE@C@A@EACAAAABCAA@AGAA@ACCEAC@@ADMBEEAC@CAOCA@@@@B@D@DABIBAD@FBD@BA@CAAAAA@C@E@AABCBEDC@C@A@@CBAF@FCFE@AAA@A@C@@ABABCFABCBC@CAAA@ABA@ADADABA@@AAE@AA@A@CAEA@C@GA@EDADAB@@AC@A@A@AA@@@E@CBCCC@ABCB@BAHAB@@AC@E@@@A@@A@ABEBA@AACA@@@E@C@CACCAA@ABADE@CAAACGCICA@AB@D@BABA@AA@A@A@ABG@AAA@ACCAA@@@GBA@@C@A@@A@@BA@A@A@CDADCDCH@N@HBB@@ACCCGAE@EA@IBA@AFC@IFEBADAB@@@@AAEBABA@C@A@ACBA@@B@F@BABA@C@@@@@AA@EAC@C@AA@@@CBA@A@A@AB@@ABCAA@@@@A@AB@DABCBEDC@AAC@AAAAAAAACBA@A@GIGBEBCB@BBDAHAHCFCDGDCHCFILCD@@@DDN@BAB@@CAAAC@C@@B@@DFBBBBA@A@AAECEAGBAB@@NJ@FAFABCBE@GDAFCFAD@FCHADEFAB@DBFCF@FCDCBEBGBEDCDEH@DAFAJ@HADABEBE@E@EACAA@@BAD@DCFCDAD@DCDABCDCDCACAAAAE@CAGAIBCBEDC@@GCEAECCCACCCCCCCAE@GEECCEEECA@ABCBC@E@C@ABABCDEDEBG@G@E@E@CAACCEAEACECCAE@A@EDGDCBCF@DAFCDCFADEDAFAJGNEBC@C@ICECEAE@GBG@CDEDEFEFEBEBGBEBG@G@G@GDA@C@EAC@KDADCDCBCBA@AA@EBE@GAEAEAECAABCACAE@EBCBC@KCE@C@G@GBE@G@E@G@IBEBCBCDCDGDCBGBGBGAAAAACCCACAACGCCC@CACC@AECKCGIGCAECEG@CDCDCBCBC@C@CAE@EBGDCBC@EAGAMCECAECEAEECCEEECAE@C@ABEAC@CBAB@BBDBF@D@FAFAFCBGBE@I@ABAHAF@D@DBF@FAHAD@BBLHFBD@D@D@DBB@BFDBD@B@F@J@DAFABCBCDEDCD@JBF@DABEBC@CACDOACCAAE@EEE@A@@BC@C@E@@BA@ABABCAGCEBABCAAA@E@EB@@@F@D@@WCWBE@IECC@AHIA@MEA@@EBAFCFAH@HDFDF@@@DIHMDGFGBADBDDD@NCPEFC@E@EAEC@KDGBC@ECACHCJGBAAAC@KDC@A@@GBELCFGHGJECAECEAI@G@MAE@EEOEGAG@C@MGQKKSEMAMIMIG[QEO@YAY@U@U@ODMFEJALERQPDzCRBRELKJO@SGGC]BOHSDGJstQJOBOGA@@@@@OOKISEUBOHGJ@JFJTTPTPVFR@HGJmZPFPHHFDLEFUNIFKRERKHQTGFGFCNBPHVFP@LDR@hGXAJEDG@MGM@GFIHELBJFLFFJNFJCFBF"],["@@JCJODSWWAAWPBBBB@B@@@B@@DF@@@B@B@@A@ABV^"]],"encodeOffsets":[[[112785,33597]],[[113712,34000]]]}}],"UTF8Encoding":true}