{"type":"FeatureCollection","features":[{"type":"Feature","id":"410923","properties":{"name":"南乐县","cp":[115.204336,36.075204],"childNum":1},"geometry":{"type":"Polygon","coordinates":["@@BQ@KAQ@@ACAAAC@A@A@@@A@CACAA@AAA@@AC@EACACAC@CAAEEAC@A@C@@ACB@AGA@C@@ABA@EG@@BEBACACAEAEB@@CF@@C@A@EGB@ECBAAA@BBC@AEC@@AC@@EGBAGD@@EB@@CD@@D@@@@BB@ED@@A@A@C@C@A@A@A@C@C@CBA@AAA@CAA@C@C@A@A@C@C@A@C@C@@CCEAOCMAQC[OGCKEQVoDODYBU@C@EDCDCFEBCBG@EAECCIIUACEAEAQBK@@@@@O@MBABGLEF@@KDCBC@G@KCK@S@GAAABM@AB@FADABAACCMECEAI@KBGFAFAJFd@D@BCBA@@AECKECB@CA@AEAAE@E@C@ACC@ADBH@BEDEBIAABDFABABKBAFHNCBB@DF@DADA@CCOHAAABCACA@AACCAA@GBCBAAKCCAMUA@C@EB@DFLE@BDKB@@@@BHEBEB@BD@BBGB@FADA@@DE@GAI@KCKAICADCBBFI@@BK@EBC@EBAEK@OCC@ACD@@AI@CDHP@FADEDBFADCDCHEB@DIRGHBBLJJJHHHHDBFFDDDBFDB@@B@B@BBFABCJ@HBHHZ@F@FADAH@FBFRXFDFFFBH@ZEbIH@DBBDBTBNFRDHFFHDJD^AH@NCHCFG@CAC@CBAFCNAHAJDF@H@BDBABB@@B@D@@BB@BFD@@DFA@FD@@FB@@@@@@BB@@BC@@FB@BBFB@C@A@@@B@@@AB@@@LB@AK@@AFB@AE@@@@@@A@@@A@@@AB@ACB@@BDA@@JBFAJEJEPCVIPIV]FSBEDGNQHKFCJETCHAFCBE@IESCG@C@ELQJIJCLAJALFHBB@HCFAD@LFVJLHHHFLDXBJBDDBR@H@DBDFBFD@@@ADBB@@BDB@BDA@@BBBGFB@AB@@B@@@D@BH@@BDB@DJ@B@@D@@@A@@CA@@CDA@CB@@A@@@A@@ACFAA@CCAAAA@CDB@CB@@CF@@@DAFAJBFDLNDDFBJ@JAF@FBBD@F@RBLBBDBHBLABABWBCFGFCLAJA"],"encodeOffsets":[[118256,37017]]}}],"UTF8Encoding":true}